Workbook

Sheet Detallado de la inversión.
C1: v4 (04-ago-2026) SAFE Lean 237.412 = Fase0 50.260 + burn 172.152 + reserva 15.000 | Day-D 187.152 | equity ~39,57% @600k | Esc.1 FCF +59.079 cash M12 246.231 | ARPF ~52
C4: Zonix Pharma — Marketplace farmacéutico VE (piloto Valencia)
C8: Descripción | E8: Cantidad Meses | F8: Monto Unitario/mes | G8: Total
C10: CONSTITUCIÓN DE LA EMPRESA (Zonix Pharma C.A.) | E10: Cant. | F10: USD/u | K10: RESUMEN INVERSIÓN LEAN (v3.9.3)
C11: Registro Mercantil + acta constitutiva | E11: 1 | F11: 1200 | G11: =E11*F11 | H11: =IF(G11=0,"",G11/G127) | K11: One-shots (legal+intro+HQ CapEx incl. alquiler Fase 0) | M11: =G91 | O11: =G18+G33+G81
C12: SENIAT — inscripción / trámites RIF | E12: 1 | F12: 600 | G12: =E12*F12 | H12: =IF(G12=0,"",G12/G127) | K12: Fase 0 operativa (MO+mkt+transporte) | M12: =G52+G39+G62
C13: Licencia / permisos municipales HQ | E13: 1 | F13: 1500 | G13: =E13*F13 | H13: =IF(G13=0,"",G13/G127) | I13: Notas / En ESTA | K13: Fase 0 total (T+0→Day-D) | M13: =G87 | N13: =M13-M11-M12 | O13: =M13-M11-G39-G62
C14: Permiso bomberos (local operativo) | E14: 1 | F14: 1100 | G14: =E14*F14 | H14: =IF(G14=0,"",G14/G127) | K14: Caja al Day-D (inicio M1) | M14: =G89
C15: Apertura cuenta bancaria empresa | E15: 1 | F15: 100 | G15: =E15*F15 | H15: =IF(G15=0,"",G15/G127) | K15: Burn 12 meses (M1–M12) | M15: =G125
C16: Sello digital + factura digital SENIAT | E16: 1 | F16: 200 | G16: =E16*F16 | H16: =IF(G16=0,"",G16/G127) | K16: Reserva caja | M16: =G126
C17: Registro marca SAPI (paralelo) | E17: 1 | F17: 350 | G17: =E17*F17 | H17: =IF(G17=0,"",G17/G127) | K17: TOTAL capital SAFE | M17: =G127 | N17: =M13+M15+M16
C18: Subtotal constitución empresa | G18: =SUM(G11:G17) | H18: =IF(G18=0,"",G18/G127) | K18: SAFE cap ref. → equity % [PENDIENTE decisión cap] | M18: =M17/600000
C20: Costos legales de constitución C.A. + local HQ (referencia real VE). No incluye permisos de farmacia aliada ni operación de medicamentos. Pack documental conservador 1.150–1.450 en ESTRUCTURA_LEGAL §1.4 — validar con abogado [PENDIENTE]. | K20: Ref. mensual post-Day-D
K21: MO operativa (subtotal) | M21: =G108
C22: MATERIA PRIMA: No aplica — ZonixPharma es servicio tecnológico (marketplace). Equivalente digital: SMS OTP, Pusher, Maps, hosting → fila «Hosting + SaaS + Firebase OTP» en ESTA SI VALE (~154 USD/mes) + contingencia en burn. | K22: Marketing mensual (subtotal) | M22: =G121
K23: v3.9.3: amueblado one-shot; alquiler en HQ one-shots (750/mes en timing); sin ops recurrentes Fase 0. Identidad categorías=timing.
C24: INTRODUCCIÓN AL MERCADO / DEMO — Lean (ancla Fase 0) | E24: Cantidad | F24: Monto Unitario | G24: Total
C25: Website landing + dominio + hosting | E25: 1 | F25: 800 | G25: =E25*F25 | H25: =IF(G25=0,"",G25/G127)
C26: Brochures y material impreso B2B | E26: 1 | F26: 1000 | G26: =E26*F26 | H26: =IF(G26=0,"",G26/G127) | J26: definir
C27: Tablets demo farmacia | E27: 4 | F27: 350 | G27: =E27*F27 | H27: =IF(G27=0,"",G27/G127)
C28: Visitas comerciales pre-Day-D | E28: 1 | F28: 500 | G28: =E28*F28 | H28: =IF(G28=0,"",G28/G127)
C29: 4x sales / Fase previa — ver MO Fase 0 (no duplicar) | E29: 0 | F29: 0 | G29: 0 | H29: arreglar
C30: Reservas operativas primer mes | E30: 1 | F30: 1000 | G30: =E30*F30 | H30: =IF(G30=0,"",G30/G127)
C31: Tarjetas presentación | E31: 4 | F31: 35 | G31: =E31*F31 | H31: arreglar
C32: Video pitch B2B farmacia (one-shot) | E32: 1 | F32: 800 | G32: =E32*F32 | H32: =IF(G32=0,"",G32/G127)
C33: Subtotal intro mercado Lean | G33: =SUM(G25:G32) | H33: =IF(G33=0,"",G33/G127)
C35: MARKETING PRE-LANZAMIENTO — Lean (3 meses, ancla)
C36: Meta Ads pre-Day-D | E36: 3 | F36: 400 | G36: =E36*F36 | H36: =IF(G36=0,"",G36/G127)
C37: Material POP / señalética | E37: 1 | F37: 600 | G37: =E37*F37 | H37: =IF(G37=0,"",G37/G127)
C38: Demos B2B adicionales | E38: 1 | F38: 450 | G38: =E38*F38 | H38: =IF(G38=0,"",G38/G127)
C39: Subtotal marketing pre-lanzamiento Lean | G39: =SUM(G36:G38) | H39: =IF(G39=0,"",G39/G127)
C41: MANO DE OBRA FASE 0 (3 meses — incluida en Fase 0, no duplicar en one-shots)
C42: 4× Sales bootstrap (350 c/u) — sueldos bajo AVGH; validar contratos [PENDIENTE]. Tarifas mensuales × 3 meses pre-Day-D. Comisiones Sales: $40/firma (estimado en ESTA, no duplicado aquí).
C44: CEO (1000/mes) | E44: 3 | F44: 1000 | G44: 3000 | H44: =IF(G44=0,"",G44/G127)
C45: Founder CEO/CTO (1000/mes) | E45: 3 | F45: 1000 | G45: 3000 | H45: arreglar
C46: Co-CEO Head Sales&Ops (1000/mes) | E46: 3 | F46: 1000 | G46: 3000 | H46: =IF(G46=0,"",G46/G127)
C47: Dev junior (Flutter/Laravel) (1000/mes) | E47: 3 | F47: 1000 | G47: 3000 | H47: =IF(G47=0,"",G47/G127)
C48: 4× Sales B2B (350/mes c/u base) | E48: 3 | F48: 1400 | G48: 4200 | H48: =IF(G48=0,"",G48/G127)
C49: CS + Community Manager (500/mes) | E49: 3 | F49: 500 | G49: 1500 | H49: =IF(G49=0,"",G49/G127)
C50: Herramientas IA (425/mes) | E50: 3 | F50: 425 | G50: 1275 | H50: =IF(G50=0,"",G50/G127)
C51: Contador + Abogado (800/mes) | E51: 3 | F51: 800 | G51: 2400 | H51: =IF(G51=0,"",G51/G127) | L51: Gasto Mensual Fase 0
C52: Subtotal mano de obra Fase 0 (3 meses) | G52: =SUM(G44:G51) | H52: =IF(G52=0,"",G52/G127) | L52: =G52/3
C54: TRANSPORTE, MOVILIDAD B2B, BRANDING (referencia desglose)
C57: Visitas comerciales Valencia (combustible / terceros) | E57: 5 | F57: 200 | G57: =E57*F57 | H57: =IF(G57=0,"",G57/G127)
C58: Tablets — ver Intro (no duplicar) | E58: 0 | F58: 0 | G58: 0 | H58: arreglar
C59: Logística material demo (POP) | E59: 1 | F59: 2500 | G59: =E59*F59 | H59: arreglar
C60: Camisa, gorras, otros | E60: 12 | F60: 35 | G60: =E60*F60 | H60: arreglar
C61: Gira medios / eventos farmacia (opcional Lean) | E61: 1 | F61: 350 | G61: =E61*F61 | H61: =IF(G61=0,"",G61/G127)
C62: Subtotal transporte referencia Fase 0 | G62: =SUM(G57:G61) | H62: =IF(G62=0,"",G62/G127)
C64: HQ Y CAPEX — Lean (ancla one-shots) | E64: Cantidad | F64: Monto Unitario | G64: Total | K64: 1 mes OPEX | L64: Esta es info que me sirve para entender cuanto es 1 mes de operaciones y que items incluye
C65: Amueblado HQ (escritorios, sillas y otros — one-shot) | E65: 1 | F65: 2250 | G65: =E65*F65 | H65: =IF(G65=0,"",G65/G127) | K65: =L52+F78+(G39/3)
C66: Adecuación HQ (pintura, señalética) | E66: 1 | F66: 1000 | G66: =E66*F66 | H66: =IF(G66=0,"",G66/G127)
C67: PC recepción / ventas | E67: 1 | F67: 800 | G67: =E67*F67 | H67: =IF(G67=0,"",G67/G127)
C68: PC administración | E68: 1 | F68: 850 | G68: =E68*F68 | H68: =IF(G68=0,"",G68/G127)
C69: PC desarrollo | E69: 2 | F69: 950 | G69: =E69*F69 | H69: =IF(G69=0,"",G69/G127)
C70: PC puesto flexible | E70: 1 | F70: 1100 | G70: =E70*F70 | H70: =IF(G70=0,"",G70/G127)
C71: Cafetera | E71: 1 | F71: 75 | G71: =E71*F71 | H71: arreglar
C72: Filtro de Agua | E72: 1 | F72: 125 | G72: =E72*F72 | H72: arreglar
C73: Microondas | E73: 1 | F73: 75 | G73: =E73*F73 | H73: arreglar
C74: Vasos y Tazas | E74: 1 | F74: 50 | G74: =E74*F74 | H74: arreglar
C75: Impresora | E75: 1 | F75: 650 | G75: =E75*F75 | H75: arreglar
C76: Resmas de papel | E76: 4 | F76: 50 | G76: =E76*F76 | H76: arreglar
C77: Articulos de oficina (boligrafos, lapices, cinta, otros) | E77: 1 | F77: 350 | G77: =E77*F77 | H77: arreglar | K77: Cuadre | L77: Este cuadre es solo ver si cuadra la sumatoria de (CONSTITUCION + INTRO + MKT + TRANSPORTE + HQ 3 MESES Y CAPEX) con las (Subfase 0a + Subfase 0b y subfase 0c). Son desgloses distintos, pero debe coincidir el total
C78: Alquiler HQ Fase 0 (3 meses × 750 — 750/mes en cronograma 0a/0b/0c) | E78: 3 | F78: 750 | G78: =E78*F78 | H78: arreglar | K78: =G81+G62+G52+G39+G33+G18
C81: Subtotal HQ y CapEx (amueblado + alquiler Fase 0 + CapEx) | G81: =SUM(G65:G78) | H81: =IF(G81=0,"",G81/G127) | K81: one shots | L81: Total one shots caculado por mi cuenta para entendelro y ver si coincide con la cedla M11
K82: =G81+G33+G18
C83: FASE 0 — OUTFLOW OPERATIVO (T+0→Day-D, bottom-up) | K83: oshots sin renta | L83: Total one shots - 1 mes renta. Calculo útil para entender el desglose de subfase 0a
C84: Sub-fase 0a (T+0 a T+30) — one-shots sin renta + transporte + mes 1 (MO+renta+mkt) | E84: 1 | F84: 33010 | G84: =E84*F84 | H84: =IF(G84=0,"",G84/G127) | K84: =K82-G78
C85: Sub-fase 0b (T+30 a T+60) — MO 7.125 + renta 750 + mkt pre 750 | E85: 1 | F85: 8625 | G85: =E85*F85 | H85: =IF(G85=0,"",G85/G127) | K85: fase 0a | L85: Total subfase 0a. Calculo manual propio para ver componentes de la cedla G84 por separado.
C86: Sub-fase 0c (T+60 a T+90) — MO 7.125 + renta 750 + mkt pre 750 | E86: 1 | F86: 8625 | G86: =E86*F86 | H86: =IF(G86=0,"",G86/G127) | K86: =K84+K65+G62
C87: Subtotal Fase 0 | G87: =SUM(G84:G86) | H87: =IF(G87=0,"",G87/G127)
C89: Caja al Day-D (TOTAL SAFE − Fase 0) | G89: =G127-G87 | H89: =IF(G89=0,"",G89/G127)
C91: TOTAL one-shots Lean (legal+intro+HQ CapEx incl. amueblado+alquiler Fase 0) | G91: =G18+G33+G81 | H91: =IF(G91=0,"",G91/G127) | K91: =G81+G33+G18
C93: Validación: Fase0 − (one-shots+MO+mkt+transporte) → 0 | G93: =G87-(G91+G52+G39+G62) | H93: =IF(G93=0,"",G93/G127) | I93: ≈ delta vs subtotal MO + HQ/servicios en Fase 0
C95: DETALLE GASTOS MENSUALES
C97: MANO DE OBRA OPERATIVA (post-Day-D — USD/mes, incluida en burn M1–M12)
C98: Espejo nómina Fase 0 mensualizada. Incluye CEO. No sumar a one-shots ni Fase 0.
C100: CEO | F100: 1000 | H100: mensual | I100: → burn Año 1
C101: Founder CEO/CTO | F101: 1000 | H101: mensual | I101: → burn Año 1
C102: Co-CEO Head Sales&Ops | F102: 1000 | H102: mensual | I102: → burn Año 1
C103: Dev junior (Flutter/Laravel) x3 | F103: 3000 | H103: mensual | I103: → burn Año 1
C104: 4× Sales B2B (base) | F104: 1400 | H104: mensual | I104: → burn Año 1 | K104: =350*6
C105: CS + Community Manager | F105: 500 | H105: mensual | I105: → burn Año 1
C106: Herramientas IA | F106: 425 | H106: mensual | I106: → burn Año 1
C107: Contador + Abogado | F107: 800 | H107: =IF(G107=0,"",G107/G127) | K107: El gasto mensual fase 0 total son 7125$ vs 9125$ mensuales después del Day D (MO OPERATIVA fija mensual), eso significa que se incrementa en 2000$/mes por la inclusión de 2 nuevos DV. ¿Es así esto?
C108: Subtotal MO operativa (fija/mes) | G108: =SUM(F100:F107)
C109: MARKETING Y OPEX MENSUAL RECURRENTE (ref. ESTA → Año 1)
C110: Incluido en burn M1–M12. No sumar a one-shots ni duplicar MO Fase 0.
C112: Alquiler HQ (mensual post-Day-D) | F112: 750 | G112: =F112 | H112: =IF(G112=0,"",G112/G127) | I112: Alquiler HQ post-Day-D — incluido en burn M1–M12
C113: Servicios oficina | F113: 200 | G113: =F113 | H113: =IF(G113=0,"",G113/G127) | I113: → ESTA: §2.3.1
C114: Impuestos varios | F114: 200 | G114: =F114 | H114: =IF(G114=0,"",G114/G127) | I114: SaaS ~120 + SMS ~34 (§2.3.1)
C115: └ Hosting cloud / SaaS (desglose) | F115: 120 | G115: 100 | I115: ~120 USD/mes — footnote, no sumar
C116: └ Firebase SMS / OTP (pico conservador) | F116: 34 | G116: 54 | I116: ~34 USD/mes — footnote, no sumar
C117: Meta Ads (prom.) | F117: 800 | G117: =F117 | H117: =IF(G117=0,"",G117/G127) | I117: → ESTA: tramos
C118: Valla pequeña (desde M3) | F118: 1500 | G118: =F118 | H118: =IF(G118=0,"",G118/G127) | I118: → ESTA / Año 1
C119: Otros OPEX | F119: 1000 | G119: =F119 | H119: =IF(G119=0,"",G119/G127) | I119: → ESTA: PRESUPUESTO §6
C120: Sales comisiones (estim. prom/mes — $40/firma) | F120: 617 | G120: =F120
C121: Subtotal marketing + opex variable/mes | G121: =SUM(G112:G120) | H121: =IF(G121=0,"",G121/G127)
H122: mensual | I122: Variable — no incluido en burn fijo Lean
C124: USE OF FUNDS 12M (post Day-D) — bottom-up | J124: Gasto Mensual
...

Sheet Hoja3
E7: Zonix Pharma — Resumen inversión (v3.9.1)
E9: A — Use of funds (TOTAL SAFE Lean) | K9: TIMELINE + RESUMEN FASE 0 (v4 (04-ago-2026))
E10: Bloque | G10: USD | H10: % del total | K10: One-shots (legal+intro+HQ CapEx incl. alquiler Fase 0) | M10: ='Detallado de la inversión.'!G91
E11: Fase 0 total (T+0→Day-D) | G11: ='Detallado de la inversión.'!G87 | H11: =G11/G15 | K11: Fase 0 operativa (MO+mkt+transporte) | M11: ='Detallado de la inversión.'!G52+'Detallado de la inversión.'!G39+'Detallado de la inversión.'!G62
E12: Burn 12 meses (M1–M12) | G12: ='Detallado de la inversión.'!G125 | H12: =G12/G15 | K12: Fase 0 total (T+0→Day-D) | M12: ='Detallado de la inversión.'!G87 | N12: =M12-M10-M11
E13: Reserva caja Lean | G13: ='Detallado de la inversión.'!G126 | H13: =G13/G15 | K13: Sub-fase 0a (T+0→T+30) | M13: ='Detallado de la inversión.'!G84
K14: Sub-fase 0b (T+30→T+60) | M14: ='Detallado de la inversión.'!G85
E15: TOTAL SAFE Lean | G15: ='Detallado de la inversión.'!G127 | H15: =SUM(H11:H13) | K15: Sub-fase 0c (T+60→T+90) | M15: ='Detallado de la inversión.'!G86
E16: Desglose Fase 0: one-shots ~22.365 + operativa ~27.895 (MO+mkt+transporte). Alquiler 3×750 dentro de HQ. v4 (04-ago-2026). | K16: Caja al Day-D (inicio M1) | M16: ='Detallado de la inversión.'!G89
K17: Burn 12 meses (M1–M12) | M17: ='Detallado de la inversión.'!G125
E18: B — Desglose operativo Fase 0 (enlace Detallado) | K18: Reserva caja | M18: ='Detallado de la inversión.'!G126
E19: Informativo — no sumar bloques al TOTAL SAFE (Sección A). Subtotal Fase 0 = modelo timing 0a–0c, no suma de columnas visibles. | K19: TOTAL capital SAFE | M19: ='Detallado de la inversión.'!G127
E20: Descripción | G20: Cant. | H20: USD/u | I20: Total USD | K20: SAFE cap ref. → equity % [PENDIENTE decisión cap] | M20: =M19/600000
E21: Constitución empresa (sin BPF/CPE farmacia)
E22: ='Detallado de la inversión.'!C11 | G22: ='Detallado de la inversión.'!E11 | H22: ='Detallado de la inversión.'!F11 | I22: ='Detallado de la inversión.'!G11 | K22: Ref. mensual post-Day-D
E23: ='Detallado de la inversión.'!C12 | G23: ='Detallado de la inversión.'!E12 | H23: ='Detallado de la inversión.'!F12 | I23: ='Detallado de la inversión.'!G12 | K23: MO operativa (subtotal) | M23: ='Detallado de la inversión.'!G108
E24: ='Detallado de la inversión.'!C13 | G24: ='Detallado de la inversión.'!E13 | H24: ='Detallado de la inversión.'!F13 | I24: ='Detallado de la inversión.'!G13 | K24: Marketing mensual (subtotal) | M24: ='Detallado de la inversión.'!G121
E25: ='Detallado de la inversión.'!C14 | G25: ='Detallado de la inversión.'!E14 | H25: ='Detallado de la inversión.'!F14 | I25: ='Detallado de la inversión.'!G14 | K25: v4 (04-ago-2026): amueblado one-shot; alquiler en HQ; sin ops recurrentes Fase 0. Categorías=timing. Unit economics → ESTA SI VALE.
E26: ='Detallado de la inversión.'!C15 | G26: ='Detallado de la inversión.'!E15 | H26: ='Detallado de la inversión.'!F15 | I26: ='Detallado de la inversión.'!G15
E27: ='Detallado de la inversión.'!C16 | G27: ='Detallado de la inversión.'!E16 | H27: ='Detallado de la inversión.'!F16 | I27: ='Detallado de la inversión.'!G16
E28: ='Detallado de la inversión.'!C17 | G28: ='Detallado de la inversión.'!E17 | H28: ='Detallado de la inversión.'!F17 | I28: ='Detallado de la inversión.'!G17
E29: ='Detallado de la inversión.'!C18 | I29: ='Detallado de la inversión.'!G18
E31: Introducción al mercado / demo
E32: ='Detallado de la inversión.'!C25 | G32: ='Detallado de la inversión.'!E25 | H32: ='Detallado de la inversión.'!F25 | I32: ='Detallado de la inversión.'!G25
E33: ='Detallado de la inversión.'!C26 | G33: ='Detallado de la inversión.'!E26 | H33: ='Detallado de la inversión.'!F26 | I33: ='Detallado de la inversión.'!G26
E34: ='Detallado de la inversión.'!C27 | G34: ='Detallado de la inversión.'!E27 | H34: ='Detallado de la inversión.'!F27 | I34: ='Detallado de la inversión.'!G27
E35: ='Detallado de la inversión.'!C28 | G35: ='Detallado de la inversión.'!E28 | H35: ='Detallado de la inversión.'!F28 | I35: ='Detallado de la inversión.'!G28
E36: ='Detallado de la inversión.'!C30 | G36: ='Detallado de la inversión.'!E30 | H36: ='Detallado de la inversión.'!F30 | I36: ='Detallado de la inversión.'!G30
E37: ='Detallado de la inversión.'!C32 | G37: ='Detallado de la inversión.'!E32 | H37: ='Detallado de la inversión.'!F32 | I37: ='Detallado de la inversión.'!G32
E38: ='Detallado de la inversión.'!C33 | I38: ='Detallado de la inversión.'!G33
E40: Marketing pre-lanzamiento (3 meses)
E41: ='Detallado de la inversión.'!C36 | G41: ='Detallado de la inversión.'!E36 | H41: ='Detallado de la inversión.'!F36 | I41: ='Detallado de la inversión.'!G36
E42: ='Detallado de la inversión.'!C37 | G42: ='Detallado de la inversión.'!E37 | H42: ='Detallado de la inversión.'!F37 | I42: ='Detallado de la inversión.'!G37
E43: ='Detallado de la inversión.'!C38 | G43: ='Detallado de la inversión.'!E38 | H43: ='Detallado de la inversión.'!F38 | I43: ='Detallado de la inversión.'!G38
E44: ='Detallado de la inversión.'!C39 | I44: ='Detallado de la inversión.'!G39
E46: Mano de obra Fase 0 (3 meses)
E47: ='Detallado de la inversión.'!C44 | G47: ='Detallado de la inversión.'!E44 | H47: ='Detallado de la inversión.'!F44 | I47: ='Detallado de la inversión.'!G44
E48: ='Detallado de la inversión.'!C46 | G48: ='Detallado de la inversión.'!E46 | H48: ='Detallado de la inversión.'!F46 | I48: ='Detallado de la inversión.'!G46
E49: ='Detallado de la inversión.'!C47 | G49: ='Detallado de la inversión.'!E47 | H49: ='Detallado de la inversión.'!F47 | I49: ='Detallado de la inversión.'!G47
E50: ='Detallado de la inversión.'!C48 | G50: ='Detallado de la inversión.'!E48 | H50: ='Detallado de la inversión.'!F48 | I50: ='Detallado de la inversión.'!G48
E51: ='Detallado de la inversión.'!C49 | G51: ='Detallado de la inversión.'!E49 | H51: ='Detallado de la inversión.'!F49 | I51: ='Detallado de la inversión.'!G49
E52: ='Detallado de la inversión.'!C50 | G52: ='Detallado de la inversión.'!E50 | H52: ='Detallado de la inversión.'!F50 | I52: ='Detallado de la inversión.'!G50
E53: ='Detallado de la inversión.'!C51 | G53: ='Detallado de la inversión.'!E51 | H53: ='Detallado de la inversión.'!F51 | I53: ='Detallado de la inversión.'!G51
E54: ='Detallado de la inversión.'!C52 | I54: ='Detallado de la inversión.'!G52
E56: Transporte B2B (referencia — no suma ancla)
E57: ='Detallado de la inversión.'!C57 | G57: ='Detallado de la inversión.'!E57 | H57: ='Detallado de la inversión.'!F57 | I57: ='Detallado de la inversión.'!G57
E58: ='Detallado de la inversión.'!C58 | G58: ='Detallado de la inversión.'!E58 | H58: ='Detallado de la inversión.'!F58 | I58: ='Detallado de la inversión.'!G58
E59: ='Detallado de la inversión.'!C61 | G59: ='Detallado de la inversión.'!E61 | H59: ='Detallado de la inversión.'!F61 | I59: ='Detallado de la inversión.'!G61
E60: ='Detallado de la inversión.'!C62 | I60: ='Detallado de la inversión.'!G62
E62: HQ y CapEx
E63: ='Detallado de la inversión.'!C65 | G63: ='Detallado de la inversión.'!E65 | H63: ='Detallado de la inversión.'!F65 | I63: ='Detallado de la inversión.'!G65
E64: ='Detallado de la inversión.'!C66 | G64: ='Detallado de la inversión.'!E66 | H64: ='Detallado de la inversión.'!F66 | I64: ='Detallado de la inversión.'!G66
E65: ='Detallado de la inversión.'!C67 | G65: ='Detallado de la inversión.'!E67 | H65: ='Detallado de la inversión.'!F67 | I65: ='Detallado de la inversión.'!G67
E66: ='Detallado de la inversión.'!C68 | G66: ='Detallado de la inversión.'!E68 | H66: ='Detallado de la inversión.'!F68 | I66: ='Detallado de la inversión.'!G68
E67: ='Detallado de la inversión.'!C69 | G67: ='Detallado de la inversión.'!E69 | H67: ='Detallado de la inversión.'!F69 | I67: ='Detallado de la inversión.'!G69
E68: ='Detallado de la inversión.'!C70 | G68: ='Detallado de la inversión.'!E70 | H68: ='Detallado de la inversión.'!F70 | I68: ='Detallado de la inversión.'!G70
E69: ='Detallado de la inversión.'!C81 | I69: ='Detallado de la inversión.'!G81
E71: Materia prima: No aplica — marketplace SaaS (~154 USD/mes hosting/SMS en ESTA SI VALE).
E73: Validación: Fase 0 − one-shots − mkt pre (ops burn) | I73: ='Detallado de la inversión.'!G93
E75: Subtotal Fase 0 (T+0→Day-D) | I75: ='Detallado de la inversión.'!G87

Sheet Hoja1
E1: Zonix Pharma — inversión Fase 0 (espejo Detallado v3.9.1) | L1: RESUMEN CAPEX (v3.9.1)
L2: Refs informativas — HQ ya en one-shots; no sumar CapEx + TOTAL SAFE.
E3: Datos ZonixPharma — enlaces a Detallado. One-shots en Hoja3 Sección A. No sumar bloques al TOTAL SAFE. Marketplace SaaS (sin rubros producción física). | L3: Inversión CapEx HQ | M3: ='Detallado de la inversión.'!G81
L4: % CapEx / TOTAL SAFE Lean | M4: =M3/'Detallado de la inversión.'!G127
E5: Descripción | G5: Cant. | H5: USD/u | I5: Total USD | J5: % SAFE | L5: TOTAL SAFE Lean (ref.) | M5: ='Detallado de la inversión.'!G127
E6: equipos | L6: Burn mensual ref. (MO+mkt) | M6: ='Detallado de la inversión.'!G107+'Detallado de la inversión.'!G121
E7: ='Detallado de la inversión.'!C67 | G7: ='Detallado de la inversión.'!E67 | H7: ='Detallado de la inversión.'!F67 | I7: ='Detallado de la inversión.'!G67 | J7: ='Detallado de la inversión.'!H67 | L7: Reserva caja (ref.) | M7: ='Detallado de la inversión.'!G126
E8: ='Detallado de la inversión.'!C68 | G8: ='Detallado de la inversión.'!E68 | H8: ='Detallado de la inversión.'!F68 | I8: ='Detallado de la inversión.'!G68 | J8: ='Detallado de la inversión.'!H68 | L8: % equity SAFE (ref.) | M8: =M5/600000
E9: ='Detallado de la inversión.'!C69 | G9: ='Detallado de la inversión.'!E69 | H9: ='Detallado de la inversión.'!F69 | I9: ='Detallado de la inversión.'!G69 | J9: ='Detallado de la inversión.'!H69
E10: ='Detallado de la inversión.'!C70 | G10: ='Detallado de la inversión.'!E70 | H10: ='Detallado de la inversión.'!F70 | I10: ='Detallado de la inversión.'!G70 | J10: ='Detallado de la inversión.'!H70 | L10: Use of funds → Hoja3 Sección A
E12: Subtotal equipos (4 PCs) | I12: =SUM('Detallado de la inversión.'!G67:G70)
E14: adecuacion
E15: ='Detallado de la inversión.'!C65 | G15: ='Detallado de la inversión.'!E65 | H15: ='Detallado de la inversión.'!F65 | I15: ='Detallado de la inversión.'!G65 | J15: ='Detallado de la inversión.'!H65
E16: ='Detallado de la inversión.'!C66 | G16: ='Detallado de la inversión.'!E66 | H16: ='Detallado de la inversión.'!F66 | I16: ='Detallado de la inversión.'!G66 | J16: ='Detallado de la inversión.'!H66
E18: Subtotal adecuación HQ | I18: =SUM('Detallado de la inversión.'!G65:G66)
E20: mano de obra
E21: ='Detallado de la inversión.'!C44 | G21: ='Detallado de la inversión.'!E44 | H21: ='Detallado de la inversión.'!F44 | I21: ='Detallado de la inversión.'!G44 | J21: ='Detallado de la inversión.'!H44
E22: ='Detallado de la inversión.'!C46 | G22: ='Detallado de la inversión.'!E46 | H22: ='Detallado de la inversión.'!F46 | I22: ='Detallado de la inversión.'!G46 | J22: ='Detallado de la inversión.'!H46
E23: ='Detallado de la inversión.'!C47 | G23: ='Detallado de la inversión.'!E47 | H23: ='Detallado de la inversión.'!F47 | I23: ='Detallado de la inversión.'!G47 | J23: ='Detallado de la inversión.'!H47
E24: ='Detallado de la inversión.'!C48 | G24: ='Detallado de la inversión.'!E48 | H24: ='Detallado de la inversión.'!F48 | I24: ='Detallado de la inversión.'!G48 | J24: ='Detallado de la inversión.'!H48
E25: ='Detallado de la inversión.'!C49 | G25: ='Detallado de la inversión.'!E49 | H25: ='Detallado de la inversión.'!F49 | I25: ='Detallado de la inversión.'!G49 | J25: ='Detallado de la inversión.'!H49
E26: ='Detallado de la inversión.'!C50 | G26: ='Detallado de la inversión.'!E50 | H26: ='Detallado de la inversión.'!F50 | I26: ='Detallado de la inversión.'!G50 | J26: ='Detallado de la inversión.'!H50
E27: ='Detallado de la inversión.'!C51 | G27: ='Detallado de la inversión.'!E51 | H27: ='Detallado de la inversión.'!F51 | I27: ='Detallado de la inversión.'!G51 | J27: ='Detallado de la inversión.'!H51
E28: ='Detallado de la inversión.'!C52 | I28: ='Detallado de la inversión.'!G52 | J28: ='Detallado de la inversión.'!H52
E30: transporte
E31: ='Detallado de la inversión.'!C57 | G31: ='Detallado de la inversión.'!E57 | H31: ='Detallado de la inversión.'!F57 | I31: ='Detallado de la inversión.'!G57 | J31: ='Detallado de la inversión.'!H57
E32: ='Detallado de la inversión.'!C58 | G32: ='Detallado de la inversión.'!E58 | H32: ='Detallado de la inversión.'!F58 | I32: ='Detallado de la inversión.'!G58 | J32: ='Detallado de la inversión.'!H58
E33: ='Detallado de la inversión.'!C61 | G33: ='Detallado de la inversión.'!E61 | H33: ='Detallado de la inversión.'!F61 | I33: ='Detallado de la inversión.'!G61 | J33: ='Detallado de la inversión.'!H61
E34: ='Detallado de la inversión.'!C62 | I34: ='Detallado de la inversión.'!G62 | J34: ='Detallado de la inversión.'!H62
E36: alquiler
E37: ='Detallado de la inversión.'!C112 | G37: ='Detallado de la inversión.'!E112 | H37: ='Detallado de la inversión.'!F112 | I37: ='Detallado de la inversión.'!G112 | J37: ='Detallado de la inversión.'!H112
E39: Depósito HQ (one-shot) incluido en bloque adecuación. Arriendo mensual post-Day-D — ref. burn Detallado.
E41: constitucion empresa y permisos
E42: ='Detallado de la inversión.'!C11 | G42: ='Detallado de la inversión.'!E11 | H42: ='Detallado de la inversión.'!F11 | I42: ='Detallado de la inversión.'!G11 | J42: ='Detallado de la inversión.'!H11
E43: ='Detallado de la inversión.'!C12 | G43: ='Detallado de la inversión.'!E12 | H43: ='Detallado de la inversión.'!F12 | I43: ='Detallado de la inversión.'!G12 | J43: ='Detallado de la inversión.'!H12
E44: ='Detallado de la inversión.'!C13 | G44: ='Detallado de la inversión.'!E13 | H44: ='Detallado de la inversión.'!F13 | I44: ='Detallado de la inversión.'!G13 | J44: ='Detallado de la inversión.'!H13
E45: ='Detallado de la inversión.'!C14 | G45: ='Detallado de la inversión.'!E14 | H45: ='Detallado de la inversión.'!F14 | I45: ='Detallado de la inversión.'!G14 | J45: ='Detallado de la inversión.'!H14
E46: ='Detallado de la inversión.'!C15 | G46: ='Detallado de la inversión.'!E15 | H46: ='Detallado de la inversión.'!F15 | I46: ='Detallado de la inversión.'!G15 | J46: ='Detallado de la inversión.'!H15
E47: ='Detallado de la inversión.'!C16 | G47: ='Detallado de la inversión.'!E16 | H47: ='Detallado de la inversión.'!F16 | I47: ='Detallado de la inversión.'!G16 | J47: ='Detallado de la inversión.'!H16
E48: ='Detallado de la inversión.'!C17 | G48: ='Detallado de la inversión.'!E17 | H48: ='Detallado de la inversión.'!F17 | I48: ='Detallado de la inversión.'!G17 | J48: ='Detallado de la inversión.'!H17
E49: ='Detallado de la inversión.'!C18 | I49: ='Detallado de la inversión.'!G18 | J49: ='Detallado de la inversión.'!H18
E51: marketing — intro mercado / demo
E52: ='Detallado de la inversión.'!C25 | G52: ='Detallado de la inversión.'!E25 | H52: ='Detallado de la inversión.'!F25 | I52: ='Detallado de la inversión.'!G25 | J52: ='Detallado de la inversión.'!H25
E53: ='Detallado de la inversión.'!C26 | G53: ='Detallado de la inversión.'!E26 | H53: ='Detallado de la inversión.'!F26 | I53: ='Detallado de la inversión.'!G26 | J53: ='Detallado de la inversión.'!H26
E54: ='Detallado de la inversión.'!C27 | G54: ='Detallado de la inversión.'!E27 | H54: ='Detallado de la inversión.'!F27 | I54: ='Detallado de la inversión.'!G27 | J54: ='Detallado de la inversión.'!H27
E55: ='Detallado de la inversión.'!C28 | G55: ='Detallado de la inversión.'!E28 | H55: ='Detallado de la inversión.'!F28 | I55: ='Detallado de la inversión.'!G28 | J55: ='Detallado de la inversión.'!H28
E56: ='Detallado de la inversión.'!C30 | G56: ='Detallado de la inversión.'!E30 | H56: ='Detallado de la inversión.'!F30 | I56: ='Detallado de la inversión.'!G30 | J56: ='Detallado de la inversión.'!H30
E57: ='Detallado de la inversión.'!C32 | G57: ='Detallado de la inversión.'!E32 | H57: ='Detallado de la inversión.'!F32 | I57: ='Detallado de la inversión.'!G32 | J57: ='Detallado de la inversión.'!H32
E58: ='Detallado de la inversión.'!C33 | I58: ='Detallado de la inversión.'!G33 | J58: ='Detallado de la inversión.'!H33
E60: marketing — pre-lanzamiento (3 meses)
E61: ='Detallado de la inversión.'!C36 | G61: ='Detallado de la inversión.'!E36 | H61: ='Detallado de la inversión.'!F36 | I61: ='Detallado de la inversión.'!G36 | J61: ='Detallado de la inversión.'!H36
E62: ='Detallado de la inversión.'!C37 | G62: ='Detallado de la inversión.'!E37 | H62: ='Detallado de la inversión.'!F37 | I62: ='Detallado de la inversión.'!G37 | J62: ='Detallado de la inversión.'!H37
E63: ='Detallado de la inversión.'!C38 | G63: ='Detallado de la inversión.'!E38 | H63: ='Detallado de la inversión.'!F38 | I63: ='Detallado de la inversión.'!G38 | J63: ='Detallado de la inversión.'!H38
E64: ='Detallado de la inversión.'!C39 | I64: ='Detallado de la inversión.'!G39 | J64: ='Detallado de la inversión.'!H39
E66: materia (SaaS / hosting / SMS — marketplace)
E67: ='Detallado de la inversión.'!C114 | G67: ='Detallado de la inversión.'!E114 | H67: ='Detallado de la inversión.'!F114 | I67: ='Detallado de la inversión.'!G114 | J67: ='Detallado de la inversión.'!H114
E69: Equivalente digital marketplace (hosting/SMS). Desglose Detallado + unit economics → ESTA SI VALE (~154 USD/mes).

Sheet Hoja2
C1: mensual
B2: Meta Ads M1-6 (USD) | C2: 800
B3: Meta Ads M7-12 (USD) | C3: 500
B4: Valla pequeña desde M3 (USD) | C4: 350

Sheet ESTA SI VALE
E3: Datos ZonixPharma — espejo Detallado/Hoja1. Bloques ESTA = vista due diligence. TOTAL SAFE oficial → Hoja3 §A. No sumar bloques al SAFE.
E7: Zonix Pharma — ESTA SI VALE (espejo Pizza v3.9.1) | M7: Zonix Pharma — Unit economics y escenarios
P8: gastos fijos mensuales (ref. burn/activas — no sumar SAFE)
E9: Descripción | G9: Cant. | H9: USD/u | I9: Total USD | J9: % SAFE | K9: Año 2 ref. | M9: Concepto | O9: Valor | S9: Fuente
E10: Factor Año 2 MO (+40%) | K10: 0.4 | M10: ARPF placeholder (USD/mes) | O10: 50 | S10: UNIT_ECONOMICS
E11: Mano de obra (Fase 0 — 3 meses) | M11: CAC farmacia (USD) | O11: 139 | S11: UNIT_ECONOMICS
E12: ='Detallado de la inversión.'!C44 | G12: ='Detallado de la inversión.'!E44 | H12: ='Detallado de la inversión.'!F44 | I12: ='Detallado de la inversión.'!G44 | J12: ='Detallado de la inversión.'!H44 | K12: =I12*(1+$K$10) | M12: Churn mensual target | O12: 0.05 | P12: Escenario margen 50%-30% | S12: UNIT_ECONOMICS
E13: ='Detallado de la inversión.'!C46 | G13: ='Detallado de la inversión.'!E46 | H13: ='Detallado de la inversión.'!F46 | I13: ='Detallado de la inversión.'!G46 | J13: ='Detallado de la inversión.'!H46 | K13: =I13*(1+$K$10) | M13: LTV (USD) | O13: 1000 | P13: Mes 1 | Q13: #VALUE! | S13: UNIT_ECONOMICS
E14: ='Detallado de la inversión.'!C47 | G14: ='Detallado de la inversión.'!E47 | H14: ='Detallado de la inversión.'!F47 | I14: ='Detallado de la inversión.'!G47 | J14: ='Detallado de la inversión.'!H47 | K14: =I14*(1+$K$10) | M14: LTV / CAC | O14: 7.2 | P14: Mes 2 | Q14: =H55 | S14: UNIT_ECONOMICS
E15: ='Detallado de la inversión.'!C48 | G15: ='Detallado de la inversión.'!E48 | H15: ='Detallado de la inversión.'!F48 | I15: ='Detallado de la inversión.'!G48 | J15: ='Detallado de la inversión.'!H48 | K15: =I15*(1+$K$10) | M15: Payback CAC (meses) | O15: 2.8 | P15: Mes 3 | Q15: =H55 | S15: UNIT_ECONOMICS
E16: ='Detallado de la inversión.'!C49 | G16: ='Detallado de la inversión.'!E49 | H16: ='Detallado de la inversión.'!F49 | I16: ='Detallado de la inversión.'!G49 | J16: ='Detallado de la inversión.'!H49 | K16: =I16*(1+$K$10) | M16: Margen bruto plataforma | O16: 0.92 | P16: TOTAL ref. | Q16: =SUM(Q13:Q15) | S16: UNIT_ECONOMICS
E17: ='Detallado de la inversión.'!C50 | G17: ='Detallado de la inversión.'!E50 | H17: ='Detallado de la inversión.'!F50 | I17: ='Detallado de la inversión.'!G50 | J17: ='Detallado de la inversión.'!H50 | K17: =I17*(1+$K$10) | M17: Cuota Basic (USD/mes) | O17: 25 | P17: Escenario margen 60%-40% | S17: PROPUESTA B2B §5
E18: ='Detallado de la inversión.'!C51 | G18: ='Detallado de la inversión.'!E51 | H18: ='Detallado de la inversión.'!F51 | I18: ='Detallado de la inversión.'!G51 | J18: ='Detallado de la inversión.'!H51 | K18: =I18*(1+$K$10) | M18: Cuota Pro (USD/mes) | O18: 40 | P18: Mes 1 | Q18: #VALUE! | S18: PROPUESTA B2B §5
E19: ='Detallado de la inversión.'!C52 | I19: ='Detallado de la inversión.'!G52 | J19: ='Detallado de la inversión.'!H52 | K19: =SUM(K12:K18) | M19: Cuota Enterprise (USD/mes) | O19: 55 | P19: Mes 2 | Q19: =H55 | S19: PROPUESTA B2B §5
M20: Mix Basic / Pro / Enterprise | O20: 60/30/10 | P20: Mes 3 | Q20: =H55 | S20: PROYECCION §1.2
E21: Factor Año 2 transporte (+30%) | K21: 0.3 | M21: Farmacias activas equilibrio Lean (M12 v3.3) | O21: 159 | P21: TOTAL ref. | Q21: =SUM(Q18:Q20) | S21: PROYECCION — 4× Sales
E22: Transporte local (B2B / demo) | P22: Escenario margen 70%-50%
E23: ='Detallado de la inversión.'!C57 | G23: ='Detallado de la inversión.'!E57 | H23: ='Detallado de la inversión.'!F57 | I23: ='Detallado de la inversión.'!G57 | J23: ='Detallado de la inversión.'!H57 | K23: =I23*(1+$K$21) | M23: ESCENARIOS CAPITAL (tiers) | P23: Mes 1 | Q23: #VALUE!
E24: ='Detallado de la inversión.'!C58 | G24: ='Detallado de la inversión.'!E58 | H24: ='Detallado de la inversión.'!F58 | I24: ='Detallado de la inversión.'!G58 | J24: ='Detallado de la inversión.'!H58 | K24: =I24*(1+$K$21) | M24: Tier | O24: Capital | P24: Mes 2 | Q24: =H55 | S24: SAFE cap
E25: ='Detallado de la inversión.'!C61 | G25: ='Detallado de la inversión.'!E61 | H25: ='Detallado de la inversión.'!F61 | I25: ='Detallado de la inversión.'!G61 | J25: ='Detallado de la inversión.'!H61 | K25: =I25*(1+$K$21) | M25: Lean — bootstrap 4× Sales (Carabobo) — capital (USD) | O25: 111988 | P25: Mes 3 | Q25: =H55 | S25: 600000
E26: ='Detallado de la inversión.'!C62 | I26: ='Detallado de la inversión.'!G62 | J26: ='Detallado de la inversión.'!H62 | K26: =SUM(K23:K25) | M26: Lean+ — 4× Sales curva ×1,15 (mismo capital Lean) — capital (USD) | O26: 111988 | P26: TOTAL ref. | Q26: =SUM(Q23:Q25) | S26: 600000
M27: Base — piso de mercado — capital (USD) | O27: 157268 | P27: 10898 | Q27: 159 | S27: 912814
E28: Constitución one-shot (sin escalación Año 2) | K28: 0 | M28: Growth — mercado pleno — capital (USD) | O28: 187478 | P28: 12698 | Q28: 159 | S28: 1205345
E29: Constitución empresa y permisos (C.A. — sin BPF/CPE piloto) | M29: Blitz — Carabobo 6× Sales — capital (USD) | O29: 184878 | P29: 11998 | Q29: 238 | S29: 1287681
E30: ='Detallado de la inversión.'!C11 | G30: ='Detallado de la inversión.'!E11 | H30: ='Detallado de la inversión.'!F11 | I30: ='Detallado de la inversión.'!G11 | J30: ='Detallado de la inversión.'!H11 | K30: =I30*(1+$K$28)
E31: ='Detallado de la inversión.'!C12 | G31: ='Detallado de la inversión.'!E12 | H31: ='Detallado de la inversión.'!F12 | I31: ='Detallado de la inversión.'!G12 | J31: ='Detallado de la inversión.'!H12 | K31: =I31*(1+$K$28) | M31: ESCENARIOS PROYECCION §7 (P10/P50/P90)
E32: ='Detallado de la inversión.'!C13 | G32: ='Detallado de la inversión.'!E13 | H32: ='Detallado de la inversión.'!F13 | I32: ='Detallado de la inversión.'!G13 | J32: ='Detallado de la inversión.'!H13 | K32: =I32*(1+$K$28) | M32: Escenario | O32: Activas M12 | P32: ARPF | Q32: Cash M12
E33: ='Detallado de la inversión.'!C14 | G33: ='Detallado de la inversión.'!E14 | H33: ='Detallado de la inversión.'!F14 | I33: ='Detallado de la inversión.'!G14 | J33: ='Detallado de la inversión.'!H14 | K33: =I33*(1+$K$28) | M33: P10 pesimista | O33: 120 | P33: 40 | Q33: 25000
E34: ='Detallado de la inversión.'!C15 | G34: ='Detallado de la inversión.'!E15 | H34: ='Detallado de la inversión.'!F15 | I34: ='Detallado de la inversión.'!G15 | J34: ='Detallado de la inversión.'!H15 | K34: =I34*(1+$K$28) | M34: P50 base | O34: 159 | P34: 50 | Q34: 40831
E35: ='Detallado de la inversión.'!C16 | G35: ='Detallado de la inversión.'!E16 | H35: ='Detallado de la inversión.'!F16 | I35: ='Detallado de la inversión.'!G16 | J35: ='Detallado de la inversión.'!H16 | K35: =I35*(1+$K$28) | M35: P90 optimista | O35: 200 | P35: 55 | Q35: 52000
E36: ='Detallado de la inversión.'!C17 | G36: ='Detallado de la inversión.'!E17 | H36: ='Detallado de la inversión.'!F17 | I36: ='Detallado de la inversión.'!G17 | J36: ='Detallado de la inversión.'!H17 | K36: =I36*(1+$K$28) | M36: Lean+ stretch (4×, curva ×1,15) | O36: 183 | P36: 50 | Q36: 49825
E37: ='Detallado de la inversión.'!C18 | I37: ='Detallado de la inversión.'!G18 | J37: ='Detallado de la inversión.'!H18 | K37: =SUM(K30:K36) | M37: Blitz stretch (6× Sales) | O37: 238 | P37: 50 | Q37: 87020
E39: Factor Año 2 intro/marketing (-50% one-shot) | K39: -0.5
E40: Introducción al mercado; primeros 3 meses
E41: ='Detallado de la inversión.'!C25 | G41: ='Detallado de la inversión.'!E25 | H41: ='Detallado de la inversión.'!F25 | I41: ='Detallado de la inversión.'!G25 | J41: ='Detallado de la inversión.'!H25 | K41: =I41*(1+$K$39)
E42: ='Detallado de la inversión.'!C26 | G42: ='Detallado de la inversión.'!E26 | H42: ='Detallado de la inversión.'!F26 | I42: ='Detallado de la inversión.'!G26 | J42: ='Detallado de la inversión.'!H26 | K42: =I42*(1+$K$39)
E43: ='Detallado de la inversión.'!C27 | G43: ='Detallado de la inversión.'!E27 | H43: ='Detallado de la inversión.'!F27 | I43: ='Detallado de la inversión.'!G27 | J43: ='Detallado de la inversión.'!H27 | K43: =I43*(1+$K$39)
E44: ='Detallado de la inversión.'!C28 | G44: ='Detallado de la inversión.'!E28 | H44: ='Detallado de la inversión.'!F28 | I44: ='Detallado de la inversión.'!G28 | J44: ='Detallado de la inversión.'!H28 | K44: =I44*(1+$K$39)
E45: ='Detallado de la inversión.'!C30 | G45: ='Detallado de la inversión.'!E30 | H45: ='Detallado de la inversión.'!F30 | I45: ='Detallado de la inversión.'!G30 | J45: ='Detallado de la inversión.'!H30 | K45: =I45*(1+$K$39)
E46: ='Detallado de la inversión.'!C32 | G46: ='Detallado de la inversión.'!E32 | H46: ='Detallado de la inversión.'!F32 | I46: ='Detallado de la inversión.'!G32 | J46: ='Detallado de la inversión.'!H32 | K46: =I46*(1+$K$39)
E47: ='Detallado de la inversión.'!C33 | I47: ='Detallado de la inversión.'!G33 | J47: ='Detallado de la inversión.'!H33 | K47: =I47*(1+$K$39)
E49: Marketing pre-lanzamiento (3 meses)
E50: ='Detallado de la inversión.'!C36 | G50: ='Detallado de la inversión.'!E36 | H50: ='Detallado de la inversión.'!F36 | I50: ='Detallado de la inversión.'!G36 | J50: ='Detallado de la inversión.'!H36 | K50: =I50*(1+$K$39)
E51: ='Detallado de la inversión.'!C37 | G51: ='Detallado de la inversión.'!E37 | H51: ='Detallado de la inversión.'!F37 | I51: ='Detallado de la inversión.'!G37 | J51: ='Detallado de la inversión.'!H37 | K51: =I51*(1+$K$39)
E52: ='Detallado de la inversión.'!C38 | G52: ='Detallado de la inversión.'!E38 | H52: ='Detallado de la inversión.'!F38 | I52: ='Detallado de la inversión.'!G38 | J52: ='Detallado de la inversión.'!H38 | K52: =I52*(1+$K$39)
E53: ='Detallado de la inversión.'!C39 | I53: ='Detallado de la inversión.'!G39 | J53: ='Detallado de la inversión.'!H39 | K53: =SUM(K41:K52)
E55: Promedio mensual intro + mkt pre (3 meses) | I55: =('Detallado de la inversión.'!G33+'Detallado de la inversión.'!G39)/3 | K55: =I55*(1+$K$39)
E56: CapEx HQ / equipos / SaaS mensual → Hoja1 + Detallado. Use-of-funds SAFE → Hoja3 §A. No sumar bloques ESTA al TOTAL SAFE.
E58: BURN MENSUAL REF. (USD/mes) — enlazado Año 1 | O58: SIMULADOR MARKETPLACE (espejo Año 1 — P50 base)
E59: Concepto | I59: USD/mes | K59: Fuente | O59: Mes | P59: Costo/activa (burn÷activas) | Q59: Farmacias activas | R59: Costo total mes | S59: ARPF (USD) | T59: Revenue mes | U59: Util./activa | V59: Utilidad mes | W59: Escenario
E60: Dev junior (Flutter/Laravel) | I60: 600 | K60: Nómina v3 | O60: 1 | P60: =IF(Q60=0,0,'Año 1 escenario 1'!C44/Q60) | Q60: ='Año 1 escenario 1'!C19 | R60: ='Año 1 escenario 1'!C44 | S60: =IF(Q60=0,0,'Año 1 escenario 1'!C25/Q60) | T60: ='Año 1 escenario 1'!C25 | U60: =S60-P60 | V60: ='Año 1 escenario 1'!C46 | W60: P50 base
E61: 4× Sales B2B (base) | I61: 1400 | K61: PRESUPUESTO §2.3 | O61: 2 | P61: =IF(Q61=0,0,'Año 1 escenario 1'!D44/Q61) | Q61: ='Año 1 escenario 1'!D19 | R61: ='Año 1 escenario 1'!D44 | S61: =IF(Q61=0,0,'Año 1 escenario 1'!D25/Q61) | T61: ='Año 1 escenario 1'!D25 | U61: =S61-P61 | V61: ='Año 1 escenario 1'!D46 | W61: P50 base
E62: CS + Community Manager | I62: 400 | O62: 3 | P62: =IF(Q62=0,0,'Año 1 escenario 1'!E44/Q62) | Q62: ='Año 1 escenario 1'!E19 | R62: ='Año 1 escenario 1'!E44 | S62: =IF(Q62=0,0,'Año 1 escenario 1'!E25/Q62) | T62: ='Año 1 escenario 1'!E25 | U62: =S62-P62 | V62: ='Año 1 escenario 1'!E46 | W62: P50 base
E63: Founder + Co-CEO | I63: 2000 | O63: 4 | P63: =IF(Q63=0,0,'Año 1 escenario 1'!F44/Q63) | Q63: ='Año 1 escenario 1'!F19 | R63: ='Año 1 escenario 1'!F44 | S63: =IF(Q63=0,0,'Año 1 escenario 1'!F25/Q63) | T63: ='Año 1 escenario 1'!F25 | U63: =S63-P63 | V63: ='Año 1 escenario 1'!F46 | W63: P50 base
E64: Herramientas IA | I64: 425 | O64: 5 | P64: =IF(Q64=0,0,'Año 1 escenario 1'!G44/Q64) | Q64: ='Año 1 escenario 1'!G19 | R64: ='Año 1 escenario 1'!G44 | S64: =IF(Q64=0,0,'Año 1 escenario 1'!G25/Q64) | T64: ='Año 1 escenario 1'!G25 | U64: =S64-P64 | V64: ='Año 1 escenario 1'!G46 | W64: P50 base
E65: Contador + Abogado | I65: 330 | O65: 6 | P65: =IF(Q65=0,0,'Año 1 escenario 1'!H44/Q65) | Q65: ='Año 1 escenario 1'!H19 | R65: ='Año 1 escenario 1'!H44 | S65: =IF(Q65=0,0,'Año 1 escenario 1'!H25/Q65) | T65: ='Año 1 escenario 1'!H25 | U65: =S65-P65 | V65: ='Año 1 escenario 1'!H46 | W65: P50 base
E66: HQ casa (arriendo + servicios) | I66: 500 | O66: 7 | P66: =IF(Q66=0,0,'Año 1 escenario 1'!I44/Q66) | Q66: ='Año 1 escenario 1'!I19 | R66: ='Año 1 escenario 1'!I44 | S66: =IF(Q66=0,0,'Año 1 escenario 1'!I25/Q66) | T66: ='Año 1 escenario 1'!I25 | U66: =S66-P66 | V66: ='Año 1 escenario 1'!I46 | W66: P50 base
E67: Servicios oficina | I67: 80 | K67: §2.3.1 | O67: 8 | P67: =IF(Q67=0,0,'Año 1 escenario 1'!J44/Q67) | Q67: ='Año 1 escenario 1'!J19 | R67: ='Año 1 escenario 1'!J44 | S67: =IF(Q67=0,0,'Año 1 escenario 1'!J25/Q67) | T67: ='Año 1 escenario 1'!J25 | U67: =S67-P67 | V67: ='Año 1 escenario 1'!J46 | W67: P50 base
E68: Hosting + SaaS + Firebase OTP | I68: 154 | K68: §2.3.1 | O68: 9 | P68: =IF(Q68=0,0,'Año 1 escenario 1'!K44/Q68) | Q68: ='Año 1 escenario 1'!K19 | R68: ='Año 1 escenario 1'!K44 | S68: =IF(Q68=0,0,'Año 1 escenario 1'!K25/Q68) | T68: ='Año 1 escenario 1'!K25 | U68: =S68-P68 | V68: ='Año 1 escenario 1'!K46 | W68: P50 base
E69: Meta Ads (prom.) | I69: 650 | K69: tramos | O69: 10 | P69: =IF(Q69=0,0,'Año 1 escenario 1'!L44/Q69) | Q69: ='Año 1 escenario 1'!L19 | R69: ='Año 1 escenario 1'!L44 | S69: =IF(Q69=0,0,'Año 1 escenario 1'!L25/Q69) | T69: ='Año 1 escenario 1'!L25 | U69: =S69-P69 | V69: ='Año 1 escenario 1'!L46 | W69: P50 base
E70: Valla pequeña (desde M3) | I70: 292 | O70: 11 | P70: =IF(Q70=0,0,'Año 1 escenario 1'!M44/Q70) | Q70: ='Año 1 escenario 1'!M19 | R70: ='Año 1 escenario 1'!M44 | S70: =IF(Q70=0,0,'Año 1 escenario 1'!M25/Q70) | T70: ='Año 1 escenario 1'!M25 | U70: =S70-P70 | V70: ='Año 1 escenario 1'!M46 | W70: P50 base
E71: Material + transporte + contingencia (incl. buffer VE 20%) | I71: 1277 | K71: PRESUPUESTO §6 | O71: 12 | P71: =IF(Q71=0,0,'Año 1 escenario 1'!N44/Q71) | Q71: ='Año 1 escenario 1'!N19 | R71: ='Año 1 escenario 1'!N44 | S71: =IF(Q71=0,0,'Año 1 escenario 1'!N25/Q71) | T71: ='Año 1 escenario 1'!N25 | U71: =S71-P71 | V71: ='Año 1 escenario 1'!N46 | W71: P50 base
E72: Sales comisiones (estim. prom/mes — $40/firma) | I72: 617 | K72: Variable — no en burn fijo Lean | O72: Total utilidad M1-M12 (P50) | V72: =SUM(V60:V71)
E73: Total burn ref. catálogo (fijos + contingencia) | I73: =SUM(I60:I70)+I71
E74: Payback inversor ilustrativo (SAFE 18.66%) | O74: Stress P10 (ARPF 40 fijo)
E75: Ver hoja Flujo Total — fila Payback (años). No promesa contractual. | O75: Mes | Q75: Activas | R75: Costo | S75: ARPF | T75: Revenue | V75: Utilidad
E76: Modelo financiero v3.9.1 — jun 2026 — pack Lanzamiento Zonix Pharma | O76: 1 | Q76: ='Año 1 escenario 1'!C19 | R76: ='Año 1 escenario 1'!C44 | S76: 40 | T76: =Q76*S76 | V76: =T76-R76 | W76: P10 stress
O77: 2 | Q77: ='Año 1 escenario 1'!D19 | R77: ='Año 1 escenario 1'!D44 | S77: 40 | T77: =Q77*S77 | V77: =T77-R77 | W77: P10 stress
O78: 3 | Q78: ='Año 1 escenario 1'!E19 | R78: ='Año 1 escenario 1'!E44 | S78: 40 | T78: =Q78*S78 | V78: =T78-R78 | W78: P10 stress
O79: 4 | Q79: ='Año 1 escenario 1'!F19 | R79: ='Año 1 escenario 1'!F44 | S79: 40 | T79: =Q79*S79 | V79: =T79-R79 | W79: P10 stress
O80: 5 | Q80: ='Año 1 escenario 1'!G19 | R80: ='Año 1 escenario 1'!G44 | S80: 40 | T80: =Q80*S80 | V80: =T80-R80 | W80: P10 stress
O81: 6 | Q81: ='Año 1 escenario 1'!H19 | R81: ='Año 1 escenario 1'!H44 | S81: 40 | T81: =Q81*S81 | V81: =T81-R81 | W81: P10 stress
O82: 7 | Q82: ='Año 1 escenario 1'!I19 | R82: ='Año 1 escenario 1'!I44 | S82: 40 | T82: =Q82*S82 | V82: =T82-R82 | W82: P10 stress
O83: 8 | Q83: ='Año 1 escenario 1'!J19 | R83: ='Año 1 escenario 1'!J44 | S83: 40 | T83: =Q83*S83 | V83: =T83-R83 | W83: P10 stress
O84: 9 | Q84: ='Año 1 escenario 1'!K19 | R84: ='Año 1 escenario 1'!K44 | S84: 40 | T84: =Q84*S84 | V84: =T84-R84 | W84: P10 stress
O85: 10 | Q85: ='Año 1 escenario 1'!L19 | R85: ='Año 1 escenario 1'!L44 | S85: 40 | T85: =Q85*S85 | V85: =T85-R85 | W85: P10 stress
O86: 11 | Q86: ='Año 1 escenario 1'!M19 | R86: ='Año 1 escenario 1'!M44 | S86: 40 | T86: =Q86*S86 | V86: =T86-R86 | W86: P10 stress
O87: 12 | Q87: ='Año 1 escenario 1'!N19 | R87: ='Año 1 escenario 1'!N44 | S87: 40 | T87: =Q87*S87 | V87: =T87-R87 | W87: P10 stress
O88: Total utilidad P10 | V88: =SUM(V76:V87)

Sheet Año 1 escenario 1
B2: ITEMS | C2: DATOS | I2: ARPF (Base Mes 1)
B3: ARPF placeholder USD/mes | C3: =C22/C19 | E3: Tasa GMV | F3: Condición Facturación | I3: Tipo Cuota | J3: Farmacias Activas Mes 1 | K3: Ingreso x Suscripción | L3: Ticket Promedio x APP | M3: Total Ticket x Mes (cada cuota) | N3: Ingreso Zonix GMV
B4: Cuota Basic USD/mes | C4: 45 | E4: 0.08 | F4: < 2000$ | I4: Cuota Basic | J4: =C7*$C$19 | K4: =J4*C4 | L4: 1000 | M4: =J4*L4 | N4: =M4*E4
B5: Cuota Pro USD/mes | C5: 60 | E5: 0.07 | F5: Entre 2001$ y 5000$ | I5: Cuota Pro | J5: =C8*$C$19 | K5: =J5*C5 | L5: 3000 | M5: =J5*L5 | N5: =M5*E5
B6: Cuota Enterprise USD/mes | C6: 70 | E6: 0.05 | F6: > 5001 | I6: Cuota Enterp | J6: =C9*$C$19 | K6: =J6*C6 | L6: 5000 | M6: =J6*L6 | N6: =M6*E6
B7: Mix Basic (ponderador) | C7: 0.6 | I7: Totales | J7: =SUM(J4:J6) | K7: =SUM(K4:K6) | L7: =SUM(L4:L6) | M7: =SUM(M4:M6) | N7: =SUM(N4:N6)
B8: Mix Pro (ponderador) | C8: 0.3 | K8: Total Ingreso x Suscripción Mes1 | L8: Ticket Promedio por Farmacia x APP | M8: Total Facturado x APP/Mes 1 | N8: Total Ingreso Zonix Mes 1.
B9: Mix Enterprise (ponderador) | C9: 0.1
B10: Churn mensual target | C10: 0.05
B11: Participación Inversor SAFE | C11: 0.25
B12: Participación Founders | C12: =1-C11
B13: Tasa descuento VAN | C13: 0.25
B14: Capital SAFE Lean (USD) | C14: =Hoja3!M19
B15: Nota escenario | C15: Lean ancla pack
B16: AÑO 1 | C16: AÑO 1
C17: Mes 1 | D17: Mes 2 | E17: Mes 3 | F17: Mes 4 | G17: Mes 5 | H17: Mes 6 | I17: Mes 7 | J17: Mes 8 | K17: Mes 9 | L17: Mes 10 | M17: Mes 11 | N17: Mes 12 | O17: TOTAL
B18: Farmacias firmadas (altas mes) | C18: 13 | D18: 13 | E18: 14 | F18: 15 | G18: 15 | H18: 16 | I18: 16 | J18: 16 | K18: 17 | L18: 17 | M18: 17 | N18: 16 | O18: =SUM(C18:N18)
B19: Farmacias activas (stock cierre mes) | C19: 40 | D19: 51 | E19: 62 | F19: 74 | G19: 85 | H19: 97 | I19: 108 | J19: 119 | K19: 130 | L19: 141 | M19: 151 | N19: 159 | O19: =N19
B21: Ingresos ($)
B22: Ingresos cuota fija B2B | C22: =C19*($C$7*$C$4+$C$8*$C$5+$C$9*$C$6) | D22: =D19*($C$7*$C$4+$C$8*$C$5+$C$9*$C$6) | E22: =E19*($C$7*$C$4+$C$8*$C$5+$C$9*$C$6) | F22: =F19*($C$7*$C$4+$C$8*$C$5+$C$9*$C$6) | G22: =G19*($C$7*$C$4+$C$8*$C$5+$C$9*$C$6) | H22: =H19*($C$7*$C$4+$C$8*$C$5+$C$9*$C$6) | I22: =I19*($C$7*$C$4+$C$8*$C$5+$C$9*$C$6) | J22: =J19*($C$7*$C$4+$C$8*$C$5+$C$9*$C$6) | ... N22: =N19*($C$7*$C$4+$C$8*$C$5+$C$9*$C$6) | O22: =SUM(C22:N22)
B23: Ingresos comisión % GMV [EDITAR] | C23: =(((C19*$C$7)*$L$4)*$E$4)+(((C19*$C$8)*$L$5)*$E$5)+(((C19*$C$9)*$L$6)*$E$6) | D23: =(((D19*$C$7)*$L$4)*$E$4)+(((D19*$C$8)*$L$5)*$E$5)+(((D19*$C$9)*$L$6)*$E$6) | E23: =(((E19*$C$7)*$L$4)*$E$4)+(((E19*$C$8)*$L$5)*$E$5)+(((E19*$C$9)*$L$6)*$E$6) | F23: =(((F19*$C$7)*$L$4)*$E$4)+(((F19*$C$8)*$L$5)*$E$5)+(((F19*$C$9)*$L$6)*$E$6) | G23: =(((G19*$C$7)*$L$4)*$E$4)+(((G19*$C$8)*$L$5)*$E$5)+(((G19*$C$9)*$L$6)*$E$6) | H23: =(((H19*$C$7)*$L$4)*$E$4)+(((H19*$C$8)*$L$5)*$E$5)+(((H19*$C$9)*$L$6)*$E$6) | I23: =(((I19*$C$7)*$L$4)*$E$4)+(((I19*$C$8)*$L$5)*$E$5)+(((I19*$C$9)*$L$6)*$E$6) | J23: =(((J19*$C$7)*$L$4)*$E$4)+(((J19*$C$8)*$L$5)*$E$5)+(((J19*$C$9)*$L$6)*$E$6) | ... N23: =(((N19*$C$7)*$L$4)*$E$4)+(((N19*$C$8)*$L$5)*$E$5)+(((N19*$C$9)*$L$6)*$E$6) | O23: =SUM(C23:N23)
O24: =SUM(C24:N24)
B25: Total Ingresos | C25: =C22+C23+C24 | D25: =D22+D23+D24 | E25: =E22+E23+E24 | F25: =F22+F23+F24 | G25: =G22+G23+G24 | H25: =H22+H23+H24 | I25: =I22+I23+I24 | J25: =J22+J23+J24 | ... N25: =N22+N23+N24 | O25: =SUM(C25:N25)
B27: Costos ($)
B28: Dev junior (Flutter/Laravel) x3 (1000 e/o) | C28: 3000 | D28: ='Detallado de la inversión.'!$F$103 | E28: ='Detallado de la inversión.'!$F$103 | F28: ='Detallado de la inversión.'!$F$103 | G28: ='Detallado de la inversión.'!$F$103 | H28: ='Detallado de la inversión.'!$F$103 | I28: ='Detallado de la inversión.'!$F$103 | J28: ='Detallado de la inversión.'!$F$103 | K28: ='Detallado de la inversión.'!$F$103 | ... N28: ='Detallado de la inversión.'!$F$103
B29: Promo Lanzamiento x 10 farmacias (50 e/o) | C29: 500 | D29: 500
B30: 4× Sales B2B | C30: ='ESTA SI VALE'!$I$61 | D30: ='Detallado de la inversión.'!$F$104 | E30: ='Detallado de la inversión.'!$F$104 | F30: ='Detallado de la inversión.'!$F$104 | G30: ='Detallado de la inversión.'!$F$104 | H30: ='Detallado de la inversión.'!$F$104 | I30: ='Detallado de la inversión.'!$F$104 | J30: ='Detallado de la inversión.'!$F$104 | K30: ='Detallado de la inversión.'!$F$104 | ... N30: ='Detallado de la inversión.'!$F$104
B31: CS + Community Manager | C31: ='ESTA SI VALE'!$I$62 | D31: ='Detallado de la inversión.'!$F$105 | E31: ='Detallado de la inversión.'!$F$105 | F31: ='Detallado de la inversión.'!$F$105 | G31: ='Detallado de la inversión.'!$F$105 | H31: ='Detallado de la inversión.'!$F$105 | I31: ='Detallado de la inversión.'!$F$105 | J31: ='Detallado de la inversión.'!$F$105 | K31: ='Detallado de la inversión.'!$F$105 | ... N31: ='Detallado de la inversión.'!$F$105
B32: Founder + Co-CEO + CEO | C32: 3000 | D32: =('Detallado de la inversión.'!$F$100+'Detallado de la inversión.'!$F$101+'Detallado de la inversión.'!$F$102) | E32: =('Detallado de la inversión.'!$F$100+'Detallado de la inversión.'!$F$101+'Detallado de la inversión.'!$F$102) | F32: =('Detallado de la inversión.'!$F$100+'Detallado de la inversión.'!$F$101+'Detallado de la inversión.'!$F$102) | G32: =('Detallado de la inversión.'!$F$100+'Detallado de la inversión.'!$F$101+'Detallado de la inversión.'!$F$102) | H32: =('Detallado de la inversión.'!$F$100+'Detallado de la inversión.'!$F$101+'Detallado de la inversión.'!$F$102) | I32: =('Detallado de la inversión.'!$F$100+'Detallado de la inversión.'!$F$101+'Detallado de la inversión.'!$F$102) | J32: =('Detallado de la inversión.'!$F$100+'Detallado de la inversión.'!$F$101+'Detallado de la inversión.'!$F$102) | K32: =('Detallado de la inversión.'!$F$100+'Detallado de la inversión.'!$F$101+'Detallado de la inversión.'!$F$102) | ... N32: =('Detallado de la inversión.'!$F$100+'Detallado de la inversión.'!$F$101+'Detallado de la inversión.'!$F$102)
B33: Herramientas IA | C33: ='ESTA SI VALE'!$I$64 | D33: ='Detallado de la inversión.'!$F$106 | E33: ='Detallado de la inversión.'!$F$106 | F33: ='Detallado de la inversión.'!$F$106 | G33: ='Detallado de la inversión.'!$F$106 | H33: ='Detallado de la inversión.'!$F$106 | I33: ='Detallado de la inversión.'!$F$106 | J33: ='Detallado de la inversión.'!$F$106 | K33: ='Detallado de la inversión.'!$F$106 | ... N33: ='Detallado de la inversión.'!$F$106
B34: Contador + Abogado | C34: ='ESTA SI VALE'!$I$65 | D34: ='Detallado de la inversión.'!$F$107 | E34: ='Detallado de la inversión.'!$F$107 | F34: ='Detallado de la inversión.'!$F$107 | G34: ='Detallado de la inversión.'!$F$107 | H34: ='Detallado de la inversión.'!$F$107 | I34: ='Detallado de la inversión.'!$F$107 | J34: ='Detallado de la inversión.'!$F$107 | K34: ='Detallado de la inversión.'!$F$107 | ... N34: ='Detallado de la inversión.'!$F$107
B35: HQ casa (arriendo) | C35: ='ESTA SI VALE'!$I$66 | D35: ='Detallado de la inversión.'!$F$112 | E35: ='Detallado de la inversión.'!$F$112 | F35: ='Detallado de la inversión.'!$F$112 | G35: ='Detallado de la inversión.'!$F$112 | H35: ='Detallado de la inversión.'!$F$112 | I35: ='Detallado de la inversión.'!$F$112 | J35: ='Detallado de la inversión.'!$F$112 | K35: ='Detallado de la inversión.'!$F$112 | ... N35: ='Detallado de la inversión.'!$F$112
B36: Servicios oficina (electricidad, agua, internet) | C36: ='ESTA SI VALE'!$I$67 | D36: ='Detallado de la inversión.'!$F$113 | E36: ='Detallado de la inversión.'!$F$113 | F36: ='Detallado de la inversión.'!$F$113 | G36: ='Detallado de la inversión.'!$F$113 | H36: ='Detallado de la inversión.'!$F$113 | I36: ='Detallado de la inversión.'!$F$113 | J36: ='Detallado de la inversión.'!$F$113 | K36: ='Detallado de la inversión.'!$F$113 | ... N36: ='Detallado de la inversión.'!$F$113
B37: Hosting + SaaS + Firebase OTP | C37: ='ESTA SI VALE'!$I$68 | D37: ='Detallado de la inversión.'!$F$115+'Detallado de la inversión.'!$F$116 | E37: ='Detallado de la inversión.'!$F$115+'Detallado de la inversión.'!$F$116 | F37: ='Detallado de la inversión.'!$F$115+'Detallado de la inversión.'!$F$116 | G37: ='Detallado de la inversión.'!$F$115+'Detallado de la inversión.'!$F$116 | H37: ='Detallado de la inversión.'!$F$115+'Detallado de la inversión.'!$F$116 | I37: ='Detallado de la inversión.'!$F$115+'Detallado de la inversión.'!$F$116 | J37: ='Detallado de la inversión.'!$F$115+'Detallado de la inversión.'!$F$116 | K37: ='Detallado de la inversión.'!$F$115+'Detallado de la inversión.'!$F$116 | ... N37: ='Detallado de la inversión.'!$F$115+'Detallado de la inversión.'!$F$116
B38: Meta Ads | C38: 800 | D38: ='Detallado de la inversión.'!$F$117 | E38: ='Detallado de la inversión.'!$F$117 | F38: ='Detallado de la inversión.'!$F$117 | G38: ='Detallado de la inversión.'!$F$117 | H38: ='Detallado de la inversión.'!$F$117 | I38: ='Detallado de la inversión.'!$F$117 | J38: ='Detallado de la inversión.'!$F$117 | K38: ='Detallado de la inversión.'!$F$117 | ... N38: ='Detallado de la inversión.'!$F$117 | O38: =SUM(C38:N38)
B39: Valla pequeña (desde M3) | C39: 0 | D39: ='Detallado de la inversión.'!$F$118 | E39: ='Detallado de la inversión.'!$F$118 | F39: ='Detallado de la inversión.'!$F$118 | G39: ='Detallado de la inversión.'!$F$118 | H39: ='Detallado de la inversión.'!$F$118 | I39: ='Detallado de la inversión.'!$F$118 | J39: ='Detallado de la inversión.'!$F$118 | K39: ='Detallado de la inversión.'!$F$118 | ... N39: ='Detallado de la inversión.'!$F$118 | O39: =SUM(C39:N39)
B40: Publicidad Exterior (otros) | C40: 2500 | D40: ='Detallado de la inversión.'!$F$119 | E40: ='Detallado de la inversión.'!$F$119 | F40: ='Detallado de la inversión.'!$F$119 | G40: ='Detallado de la inversión.'!$F$119 | H40: ='Detallado de la inversión.'!$F$119 | I40: ='Detallado de la inversión.'!$F$119 | J40: ='Detallado de la inversión.'!$F$119 | K40: ='Detallado de la inversión.'!$F$119 | ... N40: ='Detallado de la inversión.'!$F$119
B41: Impuestos Varios | D41: ='Detallado de la inversión.'!$F$114 | E41: ='Detallado de la inversión.'!$F$114 | F41: ='Detallado de la inversión.'!$F$114 | G41: ='Detallado de la inversión.'!$F$114 | H41: ='Detallado de la inversión.'!$F$114 | I41: ='Detallado de la inversión.'!$F$114 | J41: ='Detallado de la inversión.'!$F$114 | K41: ='Detallado de la inversión.'!$F$114 | ... N41: ='Detallado de la inversión.'!$F$114
B42: Comisiones (sales) | D42: ='Detallado de la inversión.'!$F$120 | E42: ='Detallado de la inversión.'!$F$120 | F42: ='Detallado de la inversión.'!$F$120 | G42: ='Detallado de la inversión.'!$F$120 | H42: ='Detallado de la inversión.'!$F$120 | I42: ='Detallado de la inversión.'!$F$120 | J42: ='Detallado de la inversión.'!$F$120 | K42: ='Detallado de la inversión.'!$F$120 | ... N42: ='Detallado de la inversión.'!$F$120
B43: Material + transporte + contingencia (incl. buffer VE 20%) | C43: 1322 | O43: =SUM(C43:N43)
B44: Total Costos | C44: =C28+C30+C31+C32+C33+C34+C35+C36+C37+C38+C39+C43 | D44: =SUM(D28:D43) | E44: =SUM(E28:E43) | F44: =SUM(F28:F43) | G44: =SUM(G28:G43) | H44: =SUM(H28:H43) | I44: =SUM(I28:I43) | J44: =SUM(J28:J43) | K44: =SUM(K28:K43) | ... N44: =SUM(N28:N43) | O44: =SUM(C44:N44)
B46: FCF | C46: =C25-C44 | D46: =D25-D44 | E46: =E25-E44 | F46: =F25-F44 | G46: =G25-G44 | H46: =H25-H44 | I46: =I25-I44 | J46: =J25-J44 | ... N46: =N25-N44 | O46: =SUM(C46:N46)
B47: FCF acumulado | C47: =C46 | D47: =C47+D46 | E47: =D47+E46 | F47: =E47+F46 | G47: =F47+G46 | H47: =G47+H46 | I47: =H47+I46 | J47: =I47+J46 | K47: =J47+K46 | ... N47: =M47+N46 | O47: =N47
B48: CCF (inversor SAFE 18,66%) | C48: =C46*$C$11 | D48: =D46*$C$11 | E48: =E46*$C$11 | F48: =F46*$C$11 | G48: =G46*$C$11 | H48: =H46*$C$11 | I48: =I46*$C$11 | J48: =J46*$C$11 | ... N48: =N46*$C$11
B49: ECF (founders 81,34%) | C49: =C46-C48 | D49: =D46-D48 | E49: =E46-E48 | F49: =F46-F48 | G49: =G46-G48 | H49: =H46-H48 | I49: =I46-I48 | J49: =J46-J48 | ... N49: =N46-N48
B51: Cash deployment (post Day-D) | C51: Mes 1 | D51: Mes 2 | E51: Mes 3 | F51: Mes 4 | G51: Mes 5 | H51: Mes 6 | I51: Mes 7 | J51: Mes 8 | K51: Mes 9 | L51: Mes 10 | M51: Mes 11 | N51: Mes 12
B52: Cash inicial mes | C52: ='Detallado de la inversión.'!G89 | D52: =C53 | E52: =D53 | F52: =E53 | G52: =F53 | H52: =G53 | I52: =H53 | J52: =I53 | K52: =J53 | ... N52: =M53
B53: Cash final mes | C53: =C52+C25-C44 | D53: =D52+D25-D44 | E53: =E52+E25-E44 | F53: =F52+F25-F44 | G53: =G52+G25-G44 | H53: =H52+H25-H44 | I53: =I52+I25-I44 | J53: =J52+J25-J44 | ... N53: =N52+N25-N44

Sheet Año 1 escenario 2
B2: ITEMS | C2: DATOS | F2: Average Revenue per Firm
B3: ARPF placeholder USD/mes | C3: 50 | F3: Fact promedio
B4: Cuota Basic USD/mes | C4: 45 | D4: 0.12 | E4: Hasta 2000 | I4: ARPF | J4: =2000*0.14
B5: Cuota Pro USD/mes | C5: 60 | D5: 0.1 | E5: 2000-5000 | J5: =4000*0.12
B6: Cuota Enterprise USD/mes | C6: 70 | D6: 0.08 | E6: mas 5000 | J6: =5000*0.11
B7: Mix Basic (ponderador) | C7: 0.6 | D7: =C7*$C$19 | E7: =D7*C4 | F7: 750 | G7: =D7*F7 | H7: =G7*D4
B8: Mix Pro (ponderador) | C8: 0.3 | D8: =C8*$C$19 | E8: =D8*C5 | F8: 2000 | G8: =D8*F8 | H8: =G8*D5 | I8: =65*0.95
B9: Mix Enterprise (ponderador) | C9: 0.1 | D9: =C9*$C$19 | E9: =D9*C6 | F9: 5000 | G9: =D9*F9 | H9: =G9*D6
B10: Churn mensual target | C10: 0.05 | D10: perdida clientes mes a mes | E10: =SUM(E7:E9) | G10: =SUM(G7:G9) | H10: =SUM(H7:H9)
B11: Participación Inversor SAFE | C11: 0.1866
B12: Participación Founders | C12: =1-C11 | H12: =C22/C19 | K12: =C22/C19
B13: Tasa descuento VAN | C13: 0.25 | F13: =40*32.5 | I13: =50-32.5 | J13: =I13*C19
B14: Capital SAFE Lean (USD) | C14: 111988
B15: Nota escenario | C15: Lean ancla pack
B16: AÑO 1 | C16: AÑO 1
C17: Mes 1 | D17: Mes 2 | E17: Mes 3 | F17: Mes 4 | G17: Mes 5 | H17: Mes 6 | I17: Mes 7 | J17: Mes 8 | K17: Mes 9 | L17: Mes 10 | M17: Mes 11 | N17: Mes 12 | O17: TOTAL
B18: Farmacias firmadas (altas mes) | C18: 13 | D18: 13 | E18: 14 | F18: 15 | G18: 15 | H18: 16 | I18: 16 | J18: 16 | K18: 17 | L18: 17 | M18: 17 | N18: 16 | O18: =SUM(C18:N18)
B19: Farmacias activas (stock cierre mes) | C19: 25 | D19: 36 | E19: 48 | F19: 59 | G19: 71 | H19: 82 | I19: 93 | J19: 104 | K19: 115 | L19: 125 | M19: 135 | N19: =(M19+N18)*0.95 | O19: =N19
D20: 36 | E20: 48 | F20: 59 | G20: 71 | H20: 82 | I20: 93 | J20: 104 | K20: 115 | L20: 125 | M20: 135 | N20: 144
B21: Ingresos ($)
B22: Ingresos cuota fija B2B | C22: =C19*($C$7*$C$4+$C$8*$C$5+$C$9*$C$6) | D22: =D19*($C$7*$C$4+$C$8*$C$5+$C$9*$C$6) | E22: =E19*($C$7*$C$4+$C$8*$C$5+$C$9*$C$6) | F22: =F19*($C$7*$C$4+$C$8*$C$5+$C$9*$C$6) | G22: =G19*($C$7*$C$4+$C$8*$C$5+$C$9*$C$6) | H22: =H19*($C$7*$C$4+$C$8*$C$5+$C$9*$C$6) | I22: =I19*($C$7*$C$4+$C$8*$C$5+$C$9*$C$6) | J22: =J19*($C$7*$C$4+$C$8*$C$5+$C$9*$C$6) | ... N22: =N19*($C$7*$C$4+$C$8*$C$5+$C$9*$C$6) | O22: =SUM(C22:N22)
B23: Ingresos comisión % GMV [EDITAR] | C23: =(((C19*$C$7)*$F$7)*$D$4)+(((C19*$C$8)*$F$8)*$D$5)+(((C19*$C$9)*$F$9)*$D$6) | D23: =(((D19*$C$7)*$F$7)*$D$4)+(((D19*$C$8)*$F$8)*$D$5)+(((D19*$C$9)*$F$9)*$D$6) | E23: =(((E19*$C$7)*$F$7)*$D$4)+(((E19*$C$8)*$F$8)*$D$5)+(((E19*$C$9)*$F$9)*$D$6) | F23: =(((F19*$C$7)*$F$7)*$D$4)+(((F19*$C$8)*$F$8)*$D$5)+(((F19*$C$9)*$F$9)*$D$6) | G23: =(((G19*$C$7)*$F$7)*$D$4)+(((G19*$C$8)*$F$8)*$D$5)+(((G19*$C$9)*$F$9)*$D$6) | H23: =(((H19*$C$7)*$F$7)*$D$4)+(((H19*$C$8)*$F$8)*$D$5)+(((H19*$C$9)*$F$9)*$D$6) | I23: =(((I19*$C$7)*$F$7)*$D$4)+(((I19*$C$8)*$F$8)*$D$5)+(((I19*$C$9)*$F$9)*$D$6) | J23: =(((J19*$C$7)*$F$7)*$D$4)+(((J19*$C$8)*$F$8)*$D$5)+(((J19*$C$9)*$F$9)*$D$6) | ... N23: =(((N19*$C$7)*$F$7)*$D$4)+(((N19*$C$8)*$F$8)*$D$5)+(((N19*$C$9)*$F$9)*$D$6) | O23: =SUM(C23:N23)
O24: =SUM(C24:N24)
B25: Total Ingresos | C25: =C22+C23+C24 | D25: =D22+D23+D24 | E25: =E22+E23+E24 | F25: =F22+F23+F24 | G25: =G22+G23+G24 | H25: =H22+H23+H24 | I25: =I22+I23+I24 | J25: =J22+J23+J24 | ... N25: =N22+N23+N24 | O25: =SUM(C25:N25)
B27: Costos ($)
B28: Dev junior (Flutter/Laravel) | C28: ='ESTA SI VALE'!$I$60 | D28: ='ESTA SI VALE'!$I$60 | E28: ='ESTA SI VALE'!$I$60 | F28: ='ESTA SI VALE'!$I$60 | G28: ='ESTA SI VALE'!$I$60 | H28: ='ESTA SI VALE'!$I$60 | I28: ='ESTA SI VALE'!$I$60 | J28: ='ESTA SI VALE'!$I$60 | ... N28: ='ESTA SI VALE'!$I$60
B29: 4× Sales B2B | C29: ='ESTA SI VALE'!$I$61 | D29: ='ESTA SI VALE'!$I$61 | E29: ='ESTA SI VALE'!$I$61 | F29: ='ESTA SI VALE'!$I$61 | G29: ='ESTA SI VALE'!$I$61 | H29: ='ESTA SI VALE'!$I$61 | I29: ='ESTA SI VALE'!$I$61 | J29: ='ESTA SI VALE'!$I$61 | ... N29: ='ESTA SI VALE'!$I$61
B30: CS + Community Manager | C30: ='ESTA SI VALE'!$I$62 | D30: ='ESTA SI VALE'!$I$62 | E30: ='ESTA SI VALE'!$I$62 | F30: ='ESTA SI VALE'!$I$62 | G30: ='ESTA SI VALE'!$I$62 | H30: ='ESTA SI VALE'!$I$62 | I30: ='ESTA SI VALE'!$I$62 | J30: ='ESTA SI VALE'!$I$62 | ... N30: ='ESTA SI VALE'!$I$62
B31: Founder + Co-CEO | C31: ='ESTA SI VALE'!$I$63 | D31: ='ESTA SI VALE'!$I$63 | E31: ='ESTA SI VALE'!$I$63 | F31: ='ESTA SI VALE'!$I$63 | G31: ='ESTA SI VALE'!$I$63 | H31: ='ESTA SI VALE'!$I$63 | I31: ='ESTA SI VALE'!$I$63 | J31: ='ESTA SI VALE'!$I$63 | ... N31: ='ESTA SI VALE'!$I$63
B32: Herramientas IA | C32: ='ESTA SI VALE'!$I$64 | D32: ='ESTA SI VALE'!$I$64 | E32: ='ESTA SI VALE'!$I$64 | F32: ='ESTA SI VALE'!$I$64 | G32: ='ESTA SI VALE'!$I$64 | H32: ='ESTA SI VALE'!$I$64 | I32: ='ESTA SI VALE'!$I$64 | J32: ='ESTA SI VALE'!$I$64 | ... N32: ='ESTA SI VALE'!$I$64
B33: Contador + Abogado | C33: ='ESTA SI VALE'!$I$65 | D33: ='ESTA SI VALE'!$I$65 | E33: ='ESTA SI VALE'!$I$65 | F33: ='ESTA SI VALE'!$I$65 | G33: ='ESTA SI VALE'!$I$65 | H33: ='ESTA SI VALE'!$I$65 | I33: ='ESTA SI VALE'!$I$65 | J33: ='ESTA SI VALE'!$I$65 | ... N33: ='ESTA SI VALE'!$I$65
B34: HQ casa (arriendo + servicios) | C34: ='ESTA SI VALE'!$I$66 | D34: ='ESTA SI VALE'!$I$66 | E34: ='ESTA SI VALE'!$I$66 | F34: ='ESTA SI VALE'!$I$66 | G34: ='ESTA SI VALE'!$I$66 | H34: ='ESTA SI VALE'!$I$66 | I34: ='ESTA SI VALE'!$I$66 | J34: ='ESTA SI VALE'!$I$66 | ... N34: ='ESTA SI VALE'!$I$66
B35: Servicios oficina (electricidad, agua, internet) | C35: ='ESTA SI VALE'!$I$67 | D35: ='ESTA SI VALE'!$I$67 | E35: ='ESTA SI VALE'!$I$67 | F35: ='ESTA SI VALE'!$I$67 | G35: ='ESTA SI VALE'!$I$67 | H35: ='ESTA SI VALE'!$I$67 | I35: ='ESTA SI VALE'!$I$67 | J35: ='ESTA SI VALE'!$I$67 | ... N35: ='ESTA SI VALE'!$I$67
B36: Hosting + SaaS + Firebase OTP | C36: ='ESTA SI VALE'!$I$68 | D36: ='ESTA SI VALE'!$I$68 | E36: ='ESTA SI VALE'!$I$68 | F36: ='ESTA SI VALE'!$I$68 | G36: ='ESTA SI VALE'!$I$68 | H36: ='ESTA SI VALE'!$I$68 | I36: ='ESTA SI VALE'!$I$68 | J36: ='ESTA SI VALE'!$I$68 | ... N36: ='ESTA SI VALE'!$I$68
B37: Meta Ads | C37: 800 | D37: 800 | E37: 800 | F37: 800 | G37: 800 | H37: 800 | I37: 500 | J37: 500 | K37: 500 | L37: 500 | M37: 500 | N37: 500 | O37: =SUM(C37:N37)
B38: Valla pequeña (desde M3) | C38: 0 | D38: 0 | E38: 350 | F38: 350 | G38: 350 | H38: 350 | I38: 350 | J38: 350 | K38: 350 | L38: 350 | M38: 350 | N38: 350 | O38: =SUM(C38:N38)
B39: Material + transporte + contingencia (incl. buffer VE 20%) | C39: 1322 | D39: 1322 | E39: 1308 | F39: 1308 | G39: 1308 | H39: 1308 | I39: 1241 | J39: 1241 | K39: 1241 | L39: 1241 | M39: 1241 | N39: 1241 | O39: =SUM(C39:N39)
B40: Total Costos | C40: =C28+C29+C30+C31+C32+C33+C34+C35+C36+C37+C38+C39 | D40: =D28+D29+D30+D31+D32+D33+D34+D35+D36+D37+D38+D39 | E40: =E28+E29+E30+E31+E32+E33+E34+E35+E36+E37+E38+E39 | F40: =F28+F29+F30+F31+F32+F33+F34+F35+F36+F37+F38+F39 | G40: =G28+G29+G30+G31+G32+G33+G34+G35+G36+G37+G38+G39 | H40: =H28+H29+H30+H31+H32+H33+H34+H35+H36+H37+H38+H39 | I40: =I28+I29+I30+I31+I32+I33+I34+I35+I36+I37+I38+I39 | J40: =J28+J29+J30+J31+J32+J33+J34+J35+J36+J37+J38+J39 | ... N40: =N28+N29+N30+N31+N32+N33+N34+N35+N36+N37+N38+N39 | O40: =SUM(C40:N40)
B42: FCF | C42: =C25-C40 | D42: =D25-D40 | E42: =E25-E40 | F42: =F25-F40 | G42: =G25-G40 | H42: =H25-H40 | I42: =I25-I40 | J42: =J25-J40 | ... N42: =N25-N40 | O42: =SUM(C42:N42)
B43: FCF acumulado | C43: =C42 | D43: =C43+D42 | E43: =D43+E42 | F43: =E43+F42 | G43: =F43+G42 | H43: =G43+H42 | I43: =H43+I42 | J43: =I43+J42 | K43: =J43+K42 | ... N43: =M43+N42 | O43: =N43
B44: CCF (inversor SAFE 18,66%) | C44: =C42*$C$11 | D44: =D42*$C$11 | E44: =E42*$C$11 | F44: =F42*$C$11 | G44: =G42*$C$11 | H44: =H42*$C$11 | I44: =I42*$C$11 | J44: =J42*$C$11 | ... N44: =N42*$C$11
B45: ECF (founders 81,34%) | C45: =C42-C44 | D45: =D42-D44 | E45: =E42-E44 | F45: =F42-F44 | G45: =G42-G44 | H45: =H42-H44 | I45: =I42-I44 | J45: =J42-J44 | ... N45: =N42-N44
B47: Cash deployment (post Day-D)
B48: Cash inicial mes | C48: ='Detallado de la inversión.'!G89 | D48: =C49 | E48: =D49 | F48: =E49 | G48: =F49 | H48: =G49 | I48: =H49 | J48: =I49 | K48: =J49 | ... N48: =M49
B49: Cash final mes | C49: =C48+C25-C40 | D49: =D48+D25-D40 | E49: =E48+E25-E40 | F49: =F48+F25-F40 | G49: =G48+G25-G40 | H49: =H48+H25-H40 | I49: =I48+I25-I40 | J49: =J48+J25-J40 | ... N49: =N48+N25-N40

Sheet Año 1 GaboTic
B2: ITEMS | C2: DATOS
B3: ARPF placeholder USD/mes | C3: 50
B4: Cuota Basic USD/mes | C4: 25
B5: Cuota Pro USD/mes | C5: 40
B6: Cuota Enterprise USD/mes | C6: 55
B7: Mix Basic (ponderador) | C7: 0.6
B8: Mix Pro (ponderador) | C8: 0.3
B9: Mix Enterprise (ponderador) | C9: 0.1
B10: Churn mensual target | C10: 0.05 | E10: Ticket Promedio | F10: 500
B11: Participación Inversor SAFE | C11: 0.1866 | E11: % GMV | F11: 0.1
B12: Participación Founders | C12: =1-C11
B13: Tasa descuento VAN | C13: 0.25
B14: Capital SAFE Lean (USD) | C14: 111988
B15: Nota escenario | C15: Lean ancla pack
B16: AÑO 1 | C16: AÑO 1
C17: Mes 1 | D17: Mes 2 | E17: Mes 3 | F17: Mes 4 | G17: Mes 5 | H17: Mes 6 | I17: Mes 7 | J17: Mes 8 | K17: Mes 9 | L17: Mes 10 | M17: Mes 11 | N17: Mes 12 | O17: TOTAL
B18: Farmacias firmadas (altas mes) | C18: 13 | D18: 13 | E18: 14 | F18: 15 | G18: 15 | H18: 16 | I18: 16 | J18: 16 | K18: 17 | L18: 17 | M18: 17 | N18: 16 | O18: =SUM(C18:N18)
B19: Farmacias activas (stock cierre mes) | C19: 40 | D19: 51 | E19: 62 | F19: 74 | G19: 85 | H19: 97 | I19: 108 | J19: 119 | K19: 130 | L19: 141 | M19: 151 | N19: 159 | O19: =N19
B21: Ingresos ($)
B22: Ingresos cuota fija B2B | C22: =C19*($C$7*$C$4+$C$8*$C$5+$C$9*$C$6) | D22: =D19*($C$7*$C$4+$C$8*$C$5+$C$9*$C$6) | E22: =E19*($C$7*$C$4+$C$8*$C$5+$C$9*$C$6) | F22: =F19*($C$7*$C$4+$C$8*$C$5+$C$9*$C$6) | G22: =G19*($C$7*$C$4+$C$8*$C$5+$C$9*$C$6) | H22: =H19*($C$7*$C$4+$C$8*$C$5+$C$9*$C$6) | I22: =I19*($C$7*$C$4+$C$8*$C$5+$C$9*$C$6) | J22: =J19*($C$7*$C$4+$C$8*$C$5+$C$9*$C$6) | ... N22: =N19*($C$7*$C$4+$C$8*$C$5+$C$9*$C$6) | O22: =SUM(C22:N22)
B23: Ingresos comisión % GMV [EDITAR] | C23: =C19*($F$10*$F$11) | D23: =D19*($F$10*$F$11) | E23: =E19*($F$10*$F$11) | F23: =F19*($F$10*$F$11) | G23: =G19*($F$10*$F$11) | H23: =H19*($F$10*$F$11) | I23: =I19*($F$10*$F$11) | J23: =J19*($F$10*$F$11) | ... N23: =N19*($F$10*$F$11) | O23: =SUM(C23:N23)
B24: Ajuste billing pack PROYECCION §1.1 | C24: =1500-(C22+C23) | D24: =2168-(D22+D23) | E24: =3100-(E22+E23) | F24: =3700-(F22+F23) | G24: =4250-(G22+G23) | H24: =4850-(H22+H23) | I24: =5400-(I22+I23) | J24: =5950-(J22+J23) | K24: =6500-(K22+K23) | L24: =7050-(L22+L23) | M24: =7550-(M22+M23) | N24: =7950-(N22+N23) | O24: =SUM(C24:N24)
B25: Total Ingresos | C25: =C22+C23+C24 | D25: =D22+D23+D24 | E25: =E22+E23+E24 | F25: =F22+F23+F24 | G25: =G22+G23+G24 | H25: =H22+H23+H24 | I25: =I22+I23+I24 | J25: =J22+J23+J24 | ... N25: =N22+N23+N24 | O25: =SUM(C25:N25)
B27: Costos ($)
B28: Dev junior (Flutter/Laravel) | C28: ='ESTA SI VALE'!$I$60 | D28: ='ESTA SI VALE'!$I$60 | E28: ='ESTA SI VALE'!$I$60 | F28: ='ESTA SI VALE'!$I$60 | G28: ='ESTA SI VALE'!$I$60 | H28: ='ESTA SI VALE'!$I$60 | I28: ='ESTA SI VALE'!$I$60 | J28: ='ESTA SI VALE'!$I$60 | ... N28: ='ESTA SI VALE'!$I$60
B29: 4× Sales B2B | C29: ='ESTA SI VALE'!$I$61 | D29: ='ESTA SI VALE'!$I$61 | E29: ='ESTA SI VALE'!$I$61 | F29: ='ESTA SI VALE'!$I$61 | G29: ='ESTA SI VALE'!$I$61 | H29: ='ESTA SI VALE'!$I$61 | I29: ='ESTA SI VALE'!$I$61 | J29: ='ESTA SI VALE'!$I$61 | ... N29: ='ESTA SI VALE'!$I$61
B30: CS + Community Manager | C30: ='ESTA SI VALE'!$I$62 | D30: ='ESTA SI VALE'!$I$62 | E30: ='ESTA SI VALE'!$I$62 | F30: ='ESTA SI VALE'!$I$62 | G30: ='ESTA SI VALE'!$I$62 | H30: ='ESTA SI VALE'!$I$62 | I30: ='ESTA SI VALE'!$I$62 | J30: ='ESTA SI VALE'!$I$62 | ... N30: ='ESTA SI VALE'!$I$62
B31: Founder + Co-CEO | C31: ='ESTA SI VALE'!$I$63 | D31: ='ESTA SI VALE'!$I$63 | E31: ='ESTA SI VALE'!$I$63 | F31: ='ESTA SI VALE'!$I$63 | G31: ='ESTA SI VALE'!$I$63 | H31: ='ESTA SI VALE'!$I$63 | I31: ='ESTA SI VALE'!$I$63 | J31: ='ESTA SI VALE'!$I$63 | ... N31: ='ESTA SI VALE'!$I$63
B32: Herramientas IA | C32: ='ESTA SI VALE'!$I$64 | D32: ='ESTA SI VALE'!$I$64 | E32: ='ESTA SI VALE'!$I$64 | F32: ='ESTA SI VALE'!$I$64 | G32: ='ESTA SI VALE'!$I$64 | H32: ='ESTA SI VALE'!$I$64 | I32: ='ESTA SI VALE'!$I$64 | J32: ='ESTA SI VALE'!$I$64 | ... N32: ='ESTA SI VALE'!$I$64
B33: Contador + Abogado | C33: ='ESTA SI VALE'!$I$65 | D33: ='ESTA SI VALE'!$I$65 | E33: ='ESTA SI VALE'!$I$65 | F33: ='ESTA SI VALE'!$I$65 | G33: ='ESTA SI VALE'!$I$65 | H33: ='ESTA SI VALE'!$I$65 | I33: ='ESTA SI VALE'!$I$65 | J33: ='ESTA SI VALE'!$I$65 | ... N33: ='ESTA SI VALE'!$I$65
B34: HQ casa (arriendo + servicios) | C34: ='ESTA SI VALE'!$I$66 | D34: ='ESTA SI VALE'!$I$66 | E34: ='ESTA SI VALE'!$I$66 | F34: ='ESTA SI VALE'!$I$66 | G34: ='ESTA SI VALE'!$I$66 | H34: ='ESTA SI VALE'!$I$66 | I34: ='ESTA SI VALE'!$I$66 | J34: ='ESTA SI VALE'!$I$66 | ... N34: ='ESTA SI VALE'!$I$66
B35: Servicios oficina (electricidad, agua, internet) | C35: ='ESTA SI VALE'!$I$67 | D35: ='ESTA SI VALE'!$I$67 | E35: ='ESTA SI VALE'!$I$67 | F35: ='ESTA SI VALE'!$I$67 | G35: ='ESTA SI VALE'!$I$67 | H35: ='ESTA SI VALE'!$I$67 | I35: ='ESTA SI VALE'!$I$67 | J35: ='ESTA SI VALE'!$I$67 | ... N35: ='ESTA SI VALE'!$I$67
B36: Hosting + SaaS + Firebase OTP | C36: ='ESTA SI VALE'!$I$68 | D36: ='ESTA SI VALE'!$I$68 | E36: ='ESTA SI VALE'!$I$68 | F36: ='ESTA SI VALE'!$I$68 | G36: ='ESTA SI VALE'!$I$68 | H36: ='ESTA SI VALE'!$I$68 | I36: ='ESTA SI VALE'!$I$68 | J36: ='ESTA SI VALE'!$I$68 | ... N36: ='ESTA SI VALE'!$I$68
B37: Meta Ads | C37: 800 | D37: 800 | E37: 800 | F37: 800 | G37: 800 | H37: 800 | I37: 500 | J37: 500 | K37: 500 | L37: 500 | M37: 500 | N37: 500 | O37: =SUM(C37:N37)
B38: Valla pequeña (desde M3) | C38: 0 | D38: 0 | E38: 350 | F38: 350 | G38: 350 | H38: 350 | I38: 350 | J38: 350 | K38: 350 | L38: 350 | M38: 350 | N38: 350 | O38: =SUM(C38:N38)
B39: Material + transporte + contingencia (incl. buffer VE 20%) | C39: 1322 | D39: 1322 | E39: 1308 | F39: 1308 | G39: 1308 | H39: 1308 | I39: 1241 | J39: 1241 | K39: 1241 | L39: 1241 | M39: 1241 | N39: 1241 | O39: =SUM(C39:N39)
B40: Total Costos | C40: =C28+C29+C30+C31+C32+C33+C34+C35+C36+C37+C38+C39 | D40: =D28+D29+D30+D31+D32+D33+D34+D35+D36+D37+D38+D39 | E40: =E28+E29+E30+E31+E32+E33+E34+E35+E36+E37+E38+E39 | F40: =F28+F29+F30+F31+F32+F33+F34+F35+F36+F37+F38+F39 | G40: =G28+G29+G30+G31+G32+G33+G34+G35+G36+G37+G38+G39 | H40: =H28+H29+H30+H31+H32+H33+H34+H35+H36+H37+H38+H39 | I40: =I28+I29+I30+I31+I32+I33+I34+I35+I36+I37+I38+I39 | J40: =J28+J29+J30+J31+J32+J33+J34+J35+J36+J37+J38+J39 | ... N40: =N28+N29+N30+N31+N32+N33+N34+N35+N36+N37+N38+N39 | O40: =SUM(C40:N40)
B42: FCF | C42: =C25-C40 | D42: =D25-D40 | E42: =E25-E40 | F42: =F25-F40 | G42: =G25-G40 | H42: =H25-H40 | I42: =I25-I40 | J42: =J25-J40 | ... N42: =N25-N40 | O42: =SUM(C42:N42)
B43: FCF acumulado | C43: =C42 | D43: =C43+D42 | E43: =D43+E42 | F43: =E43+F42 | G43: =F43+G42 | H43: =G43+H42 | I43: =H43+I42 | J43: =I43+J42 | K43: =J43+K42 | ... N43: =M43+N42 | O43: =N43
B44: CCF (inversor SAFE 18,66%) | C44: =C42*$C$11 | D44: =D42*$C$11 | E44: =E42*$C$11 | F44: =F42*$C$11 | G44: =G42*$C$11 | H44: =H42*$C$11 | I44: =I42*$C$11 | J44: =J42*$C$11 | ... N44: =N42*$C$11
B45: ECF (founders 81,34%) | C45: =C42-C44 | D45: =D42-D44 | E45: =E42-E44 | F45: =F42-F44 | G45: =G42-G44 | H45: =H42-H44 | I45: =I42-I44 | J45: =J42-J44 | ... N45: =N42-N44
B47: Cash deployment (post Day-D)
B48: Cash inicial mes | C48: ='Detallado de la inversión.'!G89 | D48: =C49 | E48: =D49 | F48: =E49 | G48: =F49 | H48: =G49 | I48: =H49 | J48: =I49 | K48: =J49 | ... N48: =M49
B49: Cash final mes | C49: =C48+C25-C40 | D49: =D48+D25-D40 | E49: =E48+E25-E40 | F49: =F48+F25-F40 | G49: =G48+G25-G40 | H49: =H48+H25-H40 | I49: =I48+I25-I40 | J49: =J48+J25-J40 | ... N49: =N48+N25-N40

Sheet Año 2
B2: ITEMS | C2: DATOS
B3: Farmacias activas cierre (ref.) | C3: ='Año 1 escenario 1'!N19
B4: Revenue anual USD [LARGO PLAZO] | C4: 102000
B5: Costos anual USD [LARGO PLAZO] | C5: 96000
B6: Participación Inversor SAFE | C6: 0.1866
B7: Participación Founders | C7: =1-C6
B8: Etiqueta | C8: PROYECCION §2
B9: AÑO 2 | C9: AÑO 2
C10: Mes 1 | D10: Mes 2 | E10: Mes 3 | F10: Mes 4 | G10: Mes 5 | H10: Mes 6 | I10: Mes 7 | J10: Mes 8 | K10: Mes 9 | L10: Mes 10 | M10: Mes 11 | N10: Mes 12 | O10: TOTAL
B11: Farmacias activas promedio mes [LARGO PLAZO] | C11: 187 | D11: 187 | E11: 187 | F11: 187 | G11: 187 | H11: 187 | I11: 187 | J11: 187 | K11: 187 | L11: 187 | M11: 187 | N11: 187 | O11: =N11
B13: Ingresos ($)
B14: Revenue plataforma | C14: 6667.17 | D14: 6667.17 | E14: 6667.17 | F14: 8046.58 | G14: 8046.58 | H14: 8046.58 | I14: 9196.09 | J14: 9196.09 | K14: 9196.09 | L14: 10090.16 | M14: 10090.16 | N14: 10090.16 | O14: =SUM(C14:N14)
B15: Total Ingresos | C15: =C14 | D15: =D14 | E15: =E14 | F15: =F14 | G15: =G14 | H15: =H14 | I15: =I14 | J15: =J14 | ... N15: =N14 | O15: =SUM(C15:N15)
B17: Costos ($)
B18: Equipo comercial + ops | C18: 2691.47 | D18: 2691.47 | E18: 2691.47 | F18: 2778.29 | G18: 2778.29 | H18: 2778.29 | I18: 2865.12 | J18: 2865.12 | K18: 2865.12 | L18: 2865.12 | M18: 2865.12 | N18: 2865.12 | O18: =SUM(C18:N18)
B19: Marketing digital | C19: 1384.19 | D19: 1384.19 | E19: 1384.19 | F19: 1428.84 | G19: 1428.84 | H19: 1428.84 | I19: 1473.49 | J19: 1473.49 | K19: 1473.49 | L19: 1473.49 | M19: 1473.49 | N19: 1473.49 | O19: =SUM(C19:N19)
B20: Hosting + SaaS | C20: 615.19 | D20: 615.19 | E20: 615.19 | F20: 635.04 | G20: 635.04 | H20: 635.04 | I20: 654.88 | J20: 654.88 | K20: 654.88 | L20: 654.88 | M20: 654.88 | N20: 654.88 | O20: =SUM(C20:N20)
B21: Legal / contador | C21: 538.29 | D21: 538.29 | E21: 538.29 | F21: 555.66 | G21: 555.66 | H21: 555.66 | I21: 573.02 | J21: 573.02 | K21: 573.02 | L21: 573.02 | M21: 573.02 | N21: 573.02 | O21: =SUM(C21:N21)
B22: HQ + servicios | C22: 922.79 | D22: 922.79 | E22: 922.79 | F22: 952.56 | G22: 952.56 | H22: 952.56 | I22: 982.33 | J22: 982.33 | K22: 982.33 | L22: 982.33 | M22: 982.33 | N22: 982.33 | O22: =SUM(C22:N22)
B23: Imprevistos / buffer | C23: 1537.98 | D23: 1537.98 | E23: 1537.98 | F23: 1587.6 | G23: 1587.6 | H23: 1587.6 | I23: 1637.21 | J23: 1637.21 | K23: 1637.21 | L23: 1637.21 | M23: 1637.21 | N23: 1637.21 | O23: =SUM(C23:N23)
B24: Total Costos | O24: =SUM(C18:N23)
B26: FCF | C26: =C15-C24 | D26: =D15-D24 | E26: =E15-E24 | F26: =F15-F24 | G26: =G15-G24 | H26: =H15-H24 | I26: =I15-I24 | J26: =J15-J24 | ... N26: =N15-N24 | O26: =SUM(C26:N26)
B27: FCF acumulado | C27: =C26 | D27: =C27+D26 | E27: =D27+E26 | F27: =E27+F26 | G27: =F27+G26 | H27: =G27+H26 | I27: =H27+I26 | J27: =I27+J26 | K27: =J27+K26 | ... N27: =M27+N26 | O27: =N27
B28: CCF (inversor SAFE 18,66%) | C28: =C26*$C$6 | D28: =D26*$C$6 | E28: =E26*$C$6 | F28: =F26*$C$6 | G28: =G26*$C$6 | H28: =H26*$C$6 | I28: =I26*$C$6 | J28: =J26*$C$6 | ... N28: =N26*$C$6
B29: ECF (founders 81,34%) | C29: =C26-C28 | D29: =D26-D28 | E29: =E26-E28 | F29: =F26-F28 | G29: =G26-G28 | H29: =H26-H28 | I29: =I26-I28 | J29: =J26-J28 | ... N29: =N26-N28

Sheet Año 3
B2: ITEMS | C2: DATOS
B3: Farmacias activas cierre (ref.) | C3: ='Año 2'!N11
B4: Revenue anual USD [LARGO PLAZO] | C4: 192000
B5: Costos anual USD [LARGO PLAZO] | C5: 108000
B6: Participación Inversor SAFE | C6: 0.1866
B7: Participación Founders | C7: =1-C6
B8: Etiqueta | C8: PROYECCION §3
B9: AÑO 3 | C9: AÑO 3
C10: Mes 1 | D10: Mes 2 | E10: Mes 3 | F10: Mes 4 | G10: Mes 5 | H10: Mes 6 | I10: Mes 7 | J10: Mes 8 | K10: Mes 9 | L10: Mes 10 | M10: Mes 11 | N10: Mes 12 | O10: TOTAL
B11: Farmacias activas promedio mes [LARGO PLAZO] | C11: 374 | D11: 374 | E11: 374 | F11: 374 | G11: 374 | H11: 374 | I11: 374 | J11: 374 | K11: 374 | L11: 374 | M11: 374 | N11: 374 | O11: =N11
B13: Ingresos ($)
B14: Revenue plataforma | C14: 12325.93 | D14: 12325.93 | E14: 12325.93 | F14: 14696.3 | G14: 14696.3 | H14: 14696.3 | I14: 17066.67 | J14: 17066.67 | K14: 17066.67 | L14: 19911.11 | M14: 19911.11 | N14: 19911.11 | O14: =SUM(C14:N14)
B15: Total Ingresos | C15: =C14 | D15: =D14 | E15: =E14 | F15: =F14 | G15: =G14 | H15: =H14 | I15: =I14 | J15: =J14 | ... N15: =N14 | O15: =SUM(C15:N15)
B17: Costos ($)
B18: Equipo comercial + ops | C18: 2625 | D18: 2625 | E18: 2625 | F18: 2975 | G18: 2975 | H18: 2975 | I18: 3325 | J18: 3325 | K18: 3325 | L18: 3675 | M18: 3675 | N18: 3675 | O18: =SUM(C18:N18)
B19: Marketing digital | C19: 1350 | D19: 1350 | E19: 1350 | F19: 1530 | G19: 1530 | H19: 1530 | I19: 1710 | J19: 1710 | K19: 1710 | L19: 1890 | M19: 1890 | N19: 1890 | O19: =SUM(C19:N19)
B20: Hosting + SaaS | C20: 600 | D20: 600 | E20: 600 | F20: 680 | G20: 680 | H20: 680 | I20: 760 | J20: 760 | K20: 760 | L20: 840 | M20: 840 | N20: 840 | O20: =SUM(C20:N20)
B21: Legal / contador | C21: 525 | D21: 525 | E21: 525 | F21: 595 | G21: 595 | H21: 595 | I21: 665 | J21: 665 | K21: 665 | L21: 735 | M21: 735 | N21: 735 | O21: =SUM(C21:N21)
B22: HQ + servicios | C22: 900 | D22: 900 | E22: 900 | F22: 1020 | G22: 1020 | H22: 1020 | I22: 1140 | J22: 1140 | K22: 1140 | L22: 1260 | M22: 1260 | N22: 1260 | O22: =SUM(C22:N22)
B23: Imprevistos / buffer | C23: 1500 | D23: 1500 | E23: 1500 | F23: 1700 | G23: 1700 | H23: 1700 | I23: 1900 | J23: 1900 | K23: 1900 | L23: 2100 | M23: 2100 | N23: 2100 | O23: =SUM(C23:N23)
B24: Total Costos | O24: =SUM(C18:N23)
B26: FCF | C26: =C15-C24 | D26: =D15-D24 | E26: =E15-E24 | F26: =F15-F24 | G26: =G15-G24 | H26: =H15-H24 | I26: =I15-I24 | J26: =J15-J24 | ... N26: =N15-N24 | O26: =SUM(C26:N26)
B27: FCF acumulado | C27: =C26 | D27: =C27+D26 | E27: =D27+E26 | F27: =E27+F26 | G27: =F27+G26 | H27: =G27+H26 | I27: =H27+I26 | J27: =I27+J26 | K27: =J27+K26 | ... N27: =M27+N26 | O27: =N27
B28: CCF (inversor SAFE 18,66%) | C28: =C26*$C$6 | D28: =D26*$C$6 | E28: =E26*$C$6 | F28: =F26*$C$6 | G28: =G26*$C$6 | H28: =H26*$C$6 | I28: =I26*$C$6 | J28: =J26*$C$6 | ... N28: =N26*$C$6
B29: ECF (founders 81,34%) | C29: =C26-C28 | D29: =D26-D28 | E29: =E26-E28 | F29: =F26-F28 | G29: =G26-G28 | H29: =H26-H28 | I29: =I26-I28 | J29: =J26-J28 | ... N29: =N26-N28

Sheet Año 4
B2: ITEMS | C2: DATOS
B3: Farmacias activas cierre (ref.) | C3: ='Año 3'!N11
B4: Revenue anual USD [LARGO PLAZO] | C4: 240000
B5: Costos anual USD [LARGO PLAZO] | C5: 130000
B6: Participación Inversor SAFE | C6: 0.1866
B7: Participación Founders | C7: =1-C6
B8: Etiqueta | C8: SUPUESTO MODELO
B9: AÑO 4 | C9: AÑO 4
C10: Mes 1 | D10: Mes 2 | E10: Mes 3 | F10: Mes 4 | G10: Mes 5 | H10: Mes 6 | I10: Mes 7 | J10: Mes 8 | K10: Mes 9 | L10: Mes 10 | M10: Mes 11 | N10: Mes 12 | O10: TOTAL
B11: Farmacias activas promedio mes [LARGO PLAZO] | C11: 442 | D11: 442 | E11: 442 | F11: 442 | G11: 442 | H11: 442 | I11: 442 | J11: 442 | K11: 442 | L11: 442 | M11: 442 | N11: 442 | O11: =N11
B13: Ingresos ($)
B14: Revenue plataforma | C14: 20000 | D14: 20000 | E14: 20000 | F14: 20000 | G14: 20000 | H14: 20000 | I14: 20000 | J14: 20000 | K14: 20000 | L14: 20000 | M14: 20000 | N14: 20000 | O14: =SUM(C14:N14)
B15: Total Ingresos | C15: =C14 | D15: =D14 | E15: =E14 | F15: =F14 | G15: =G14 | H15: =H14 | I15: =I14 | J15: =J14 | ... N15: =N14 | O15: =SUM(C15:N15)
B17: Costos ($)
B18: Equipo comercial + ops | C18: 3791.67 | D18: 3791.67 | E18: 3791.67 | F18: 3791.67 | G18: 3791.67 | H18: 3791.67 | I18: 3791.67 | J18: 3791.67 | K18: 3791.67 | L18: 3791.67 | M18: 3791.67 | N18: 3791.67 | O18: =SUM(C18:N18)
B19: Marketing digital | C19: 1950 | D19: 1950 | E19: 1950 | F19: 1950 | G19: 1950 | H19: 1950 | I19: 1950 | J19: 1950 | K19: 1950 | L19: 1950 | M19: 1950 | N19: 1950 | O19: =SUM(C19:N19)
B20: Hosting + SaaS | C20: 866.67 | D20: 866.67 | E20: 866.67 | F20: 866.67 | G20: 866.67 | H20: 866.67 | I20: 866.67 | J20: 866.67 | K20: 866.67 | L20: 866.67 | M20: 866.67 | N20: 866.67 | O20: =SUM(C20:N20)
B21: Legal / contador | C21: 758.33 | D21: 758.33 | E21: 758.33 | F21: 758.33 | G21: 758.33 | H21: 758.33 | I21: 758.33 | J21: 758.33 | K21: 758.33 | L21: 758.33 | M21: 758.33 | N21: 758.33 | O21: =SUM(C21:N21)
B22: HQ + servicios | C22: 1300 | D22: 1300 | E22: 1300 | F22: 1300 | G22: 1300 | H22: 1300 | I22: 1300 | J22: 1300 | K22: 1300 | L22: 1300 | M22: 1300 | N22: 1300 | O22: =SUM(C22:N22)
B23: Imprevistos / buffer | C23: 2166.67 | D23: 2166.67 | E23: 2166.67 | F23: 2166.67 | G23: 2166.67 | H23: 2166.67 | I23: 2166.67 | J23: 2166.67 | K23: 2166.67 | L23: 2166.67 | M23: 2166.67 | N23: 2166.67 | O23: =SUM(C23:N23)
B24: Total Costos | O24: =SUM(C18:N23)
B26: FCF | C26: =C15-C24 | D26: =D15-D24 | E26: =E15-E24 | F26: =F15-F24 | G26: =G15-G24 | H26: =H15-H24 | I26: =I15-I24 | J26: =J15-J24 | ... N26: =N15-N24 | O26: =SUM(C26:N26)
B27: FCF acumulado | C27: =C26 | D27: =C27+D26 | E27: =D27+E26 | F27: =E27+F26 | G27: =F27+G26 | H27: =G27+H26 | I27: =H27+I26 | J27: =I27+J26 | K27: =J27+K26 | ... N27: =M27+N26 | O27: =N27
B28: CCF (inversor SAFE 18,66%) | C28: =C26*$C$6 | D28: =D26*$C$6 | E28: =E26*$C$6 | F28: =F26*$C$6 | G28: =G26*$C$6 | H28: =H26*$C$6 | I28: =I26*$C$6 | J28: =J26*$C$6 | ... N28: =N26*$C$6
B29: ECF (founders 81,34%) | C29: =C26-C28 | D29: =D26-D28 | E29: =E26-E28 | F29: =F26-F28 | G29: =G26-G28 | H29: =H26-H28 | I29: =I26-I28 | J29: =J26-J28 | ... N29: =N26-N28

Sheet Año 5
B2: ITEMS | C2: DATOS
B3: Farmacias activas cierre (ref.) | C3: ='Año 4'!N11
B4: Revenue anual USD [LARGO PLAZO] | C4: 300000
B5: Costos anual USD [LARGO PLAZO] | C5: 150000
B6: Participación Inversor SAFE | C6: 0.1866
B7: Participación Founders | C7: =1-C6
B8: Etiqueta | C8: SUPUESTO MODELO
B9: AÑO 5 | C9: AÑO 5
C10: Mes 1 | D10: Mes 2 | E10: Mes 3 | F10: Mes 4 | G10: Mes 5 | H10: Mes 6 | I10: Mes 7 | J10: Mes 8 | K10: Mes 9 | L10: Mes 10 | M10: Mes 11 | N10: Mes 12 | O10: TOTAL
B11: Farmacias activas promedio mes [LARGO PLAZO] | C11: 510 | D11: 510 | E11: 510 | F11: 510 | G11: 510 | H11: 510 | I11: 510 | J11: 510 | K11: 510 | L11: 510 | M11: 510 | N11: 510 | O11: =N11
B13: Ingresos ($)
B14: Revenue plataforma | C14: 25000 | D14: 25000 | E14: 25000 | F14: 25000 | G14: 25000 | H14: 25000 | I14: 25000 | J14: 25000 | K14: 25000 | L14: 25000 | M14: 25000 | N14: 25000 | O14: =SUM(C14:N14)
B15: Total Ingresos | C15: =C14 | D15: =D14 | E15: =E14 | F15: =F14 | G15: =G14 | H15: =H14 | I15: =I14 | J15: =J14 | ... N15: =N14 | O15: =SUM(C15:N15)
B17: Costos ($)
B18: Equipo comercial + ops | C18: 4375 | D18: 4375 | E18: 4375 | F18: 4375 | G18: 4375 | H18: 4375 | I18: 4375 | J18: 4375 | K18: 4375 | L18: 4375 | M18: 4375 | N18: 4375 | O18: =SUM(C18:N18)
B19: Marketing digital | C19: 2250 | D19: 2250 | E19: 2250 | F19: 2250 | G19: 2250 | H19: 2250 | I19: 2250 | J19: 2250 | K19: 2250 | L19: 2250 | M19: 2250 | N19: 2250 | O19: =SUM(C19:N19)
B20: Hosting + SaaS | C20: 1000 | D20: 1000 | E20: 1000 | F20: 1000 | G20: 1000 | H20: 1000 | I20: 1000 | J20: 1000 | K20: 1000 | L20: 1000 | M20: 1000 | N20: 1000 | O20: =SUM(C20:N20)
B21: Legal / contador | C21: 875 | D21: 875 | E21: 875 | F21: 875 | G21: 875 | H21: 875 | I21: 875 | J21: 875 | K21: 875 | L21: 875 | M21: 875 | N21: 875 | O21: =SUM(C21:N21)
B22: HQ + servicios | C22: 1500 | D22: 1500 | E22: 1500 | F22: 1500 | G22: 1500 | H22: 1500 | I22: 1500 | J22: 1500 | K22: 1500 | L22: 1500 | M22: 1500 | N22: 1500 | O22: =SUM(C22:N22)
B23: Imprevistos / buffer | C23: 2500 | D23: 2500 | E23: 2500 | F23: 2500 | G23: 2500 | H23: 2500 | I23: 2500 | J23: 2500 | K23: 2500 | L23: 2500 | M23: 2500 | N23: 2500 | O23: =SUM(C23:N23)
B24: Total Costos | O24: =SUM(C18:N23)
B26: FCF | C26: =C15-C24 | D26: =D15-D24 | E26: =E15-E24 | F26: =F15-F24 | G26: =G15-G24 | H26: =H15-H24 | I26: =I15-I24 | J26: =J15-J24 | ... N26: =N15-N24 | O26: =SUM(C26:N26)
B27: FCF acumulado | C27: =C26 | D27: =C27+D26 | E27: =D27+E26 | F27: =E27+F26 | G27: =F27+G26 | H27: =G27+H26 | I27: =H27+I26 | J27: =I27+J26 | K27: =J27+K26 | ... N27: =M27+N26 | O27: =N27
B28: CCF (inversor SAFE 18,66%) | C28: =C26*$C$6 | D28: =D26*$C$6 | E28: =E26*$C$6 | F28: =F26*$C$6 | G28: =G26*$C$6 | H28: =H26*$C$6 | I28: =I26*$C$6 | J28: =J26*$C$6 | ... N28: =N26*$C$6
B29: ECF (founders 81,34%) | C29: =C26-C28 | D29: =D26-D28 | E29: =E26-E28 | F29: =F26-F28 | G29: =G26-G28 | H29: =H26-H28 | I29: =I26-I28 | J29: =J26-J28 | ... N29: =N26-N28

Sheet Flujo Total
B2: PREMISAS DEL PROYECTO E INDICADORES — Zonix Pharma
B4: ITEMS | C4: DATOS
B5: ARPF placeholder USD/mes | C5: 52
B6: Participación Inversor SAFE | C6: 0.3957
B7: Participación Founders | C7: =1-C6
B8: Tasa Descuento | C8: 0.25
B9: Inversión Inicial (wire T+0) | C9: -237412
B10: SAFE post-money cap Lean | C10: 600000
B11: Nota reparto | C11: Ilustrativo — no sustituye term sheet SAFE
B16: Concepto | D16: Año 1 | E16: Año 2 | F16: Año 3 | G16: Año 4 | H16: Año 5 | I16: TOTAL
B17: Farmacias activas cierre | D17: ='Año 1 escenario 1'!N19 | E17: ='Año 2'!N11 | F17: ='Año 3'!N11 | G17: ='Año 4'!N11 | H17: ='Año 5'!N11
B18: Total Ingresos anual | D18: ='Año 1 escenario 1'!O25 | E18: ='Año 2'!O15 | F18: ='Año 3'!O15 | G18: ='Año 4'!O15 | H18: ='Año 5'!O15 | I18: =SUM(D18:H18)
B19: Total Costos anual | D19: ='Año 1 escenario 1'!O44 | E19: ='Año 2'!O24 | F19: ='Año 3'!O24 | G19: ='Año 4'!O24 | H19: ='Año 5'!O24 | I19: =SUM(D19:H19)
B20: FCF anual | D20: =D18-D19 | E20: =E18-E19 | F20: =F18-F19 | G20: =G18-G19 | H20: =H18-H19 | I20: =SUM(D20:H20)
B21: FCF acumulado | D21: =D20 | E21: =D21+E20 | F21: =E21+F20 | G21: =F21+G20 | H21: =G21+H20
B22: CCF (inversor SAFE) | D22: =D20*$C$6 | E22: =E20*$C$6 | F22: =F20*$C$6 | G22: =G20*$C$6 | H22: =H20*$C$6 | K22: CCF acum Y5 | L22: Por recuperar Y5
B23: CCF acumulado (inversor) | D23: =D22 | E23: =D23+E22 | F23: =E23+F22 | G23: =F23+G22 | H23: =G23+H22 | K23: =H23
B24: Por recuperar inversor (SAFE) | D24: =MAX(0,-$C$9-D23) | E24: =MAX(0,-$C$9-E23) | F24: =MAX(0,-$C$9-F23) | G24: =MAX(0,-$C$9-G23) | H24: =MAX(0,-$C$9-H23) | L24: =H24
B25: ECF (founders) | D25: =D20-D22 | E25: =E20-E22 | F25: =F20-F22 | G25: =G20-G22 | H25: =H20-H22
J27: Flujo IRR
J28: -237412
J29: =D20
J30: =E20
J31: =F20
J32: =G20
J33: =H20
B34: VP Flujos(5) | C34: =NPV($C$8,D20:H20)
B35: VAN(5) | C35: =C34+C9
B36: VP Flujos(3) | C36: =NPV($C$8,D20:F20)
B37: VAN(3) | C37: =C36+C9
B38: TIR(5) | C38: =IRR(J28:J33)
B39: TIR(3) | C39: =IRR(J28:J31)
B40: Tasa Requerida (r) | C40: =$C$8
B41: Payback inversor (años, ilustrativo) | C41: =IF(H23>=ABS($C$9),5,IF(G23>=ABS($C$9),4,IF(F23>=ABS($C$9),3,IF(E23>=ABS($C$9),2,IF(D23>=ABS($C$9),1,"[LARGO PLAZO]")))))
B42: % SAFE recuperado (CCF acum Y5, ilustrativo) | C42: =H23/ABS($C$9)
B43: Lectura payback | C43: =IF(C41="[LARGO PLAZO]","CCF acum Y5 no cubre SAFE — ver % recuperado","")
B45: NOTA: Reparto CCF/ECF ilustrativo post-cap SAFE 18,66%. No cláusula de dividendos.

Sheet Tasa Crecimiento
B2: TASAS DE CRECIMIENTO — Zonix Pharma
C4: Año 1 | D4: Año 2 | E4: Año 3 | F4: Año 4 | G4: Año 5
B6: Revenue anual % vs año anterior | D6: =IF(C8=0,"",(D8-C8)/C8) | E6: =IF(D8=0,"",(E8-D8)/D8) | F6: =IF(E8=0,"",(F8-E8)/E8) | G6: =IF(F8=0,"",(G8-F8)/F8)
B7: Farmacias activas cierre | C7: ='Año 1 escenario 1'!N19 | D7: ='Año 2'!N11 | E7: ='Año 3'!N11 | F7: ='Año 4'!N11 | G7: ='Año 5'!N11
B8: Revenue anual USD | C8: ='Año 1 escenario 1'!O25 | D8: ='Año 2'!O15 | E8: ='Año 3'!O15 | F8: ='Año 4'!O15 | G8: ='Año 5'!O15
B9: ARPF placeholder USD | C9: 50 | D9: 52 | E9: 55 | F9: 58 | G9: 60
B10: Burn prom. mensual USD | C10: ='Año 1 escenario 1'!O44/12 | D10: ='Año 2'!O24/12 | E10: ='Año 3'!O24/12 | F10: ='Año 4'!O24/12 | G10: ='Año 5'!O24/12
B11: Etiqueta | C11: ancla | D11: PROY §2 | E11: PROY §3 | F11: SUPUESTO | G11: SUPUESTO
